{"version":2,"kind":"Notebook","sha256":"26b8067b96f2418bf8db2e802a7820773ed89f3eb404d41d1c6058b0f66ae36d","slug":"notebooks.healpix","location":"/notebooks/00-healpix.ipynb","dependencies":[],"frontmatter":{"title":"HEALPix Overview","content_includes_title":false,"kernelspec":{"name":"python3","display_name":"Python 3 (ipykernel)","language":"python"},"authors":[{"nameParsed":{"literal":"Project Pythia Community","given":"Project Pythia","family":"Community"},"name":"Project Pythia Community","url":"https://projectpythia.org/","id":"contributors-myst-generated-uid-0"}],"open_access":true,"license":{"content":{"id":"CC-BY-4.0","url":"https://creativecommons.org/licenses/by/4.0/","name":"Creative Commons Attribution 4.0 International","free":true,"CC":true},"code":{"id":"Apache-2.0","url":"https://opensource.org/licenses/Apache-2.0","name":"Apache License 2.0","free":true,"osi":true}},"github":"https://github.com/projectpythia/healpix-cookbook","copyright":"2025","affiliations":[{"id":"UAlbany","name":"University at Albany (SUNY)","department":"Atmospheric and Environmental Sciences","url":"https://www.albany.edu/daes"},{"id":"CISL","name":"NSF National Center for Atmospheric Research","department":"Computational and Information Systems Lab","url":"https://www.cisl.ucar.edu"},{"id":"Unidata","name":"NSF Unidata","url":"https://www.unidata.ucar.edu"},{"id":"Argonne","name":"Argonne National Laboratory","department":"Environmental Science Division","url":"https://www.anl.gov/evs"},{"id":"CarbonPlan","name":"CarbonPlan","url":"https://carbonplan.org"},{"id":"NVIDIA","name":"NVIDIA Corporation","url":"https://www.nvidia.com/"}],"numbering":{"title":{"offset":1}},"edit_url":"https://github.com/projectpythia/healpix-cookbook/blob/main/notebooks/00-healpix.ipynb","thumbnail":"/healpix-cookbook/build/905fe1ae8d9a0e41b8fe13928c963fdd.jpeg","exports":[{"format":"ipynb","filename":"00-healpix.ipynb","url":"/healpix-cookbook/build/00-healpix-5401985100b49daf51ee6cac7bad29c1.ipynb"}]},"widgets":{},"mdast":{"type":"root","children":[{"type":"block","kind":"notebook-content","children":[{"type":"paragraph","position":{"start":{"line":3,"column":1},"end":{"line":3,"column":1}},"children":[{"type":"text","value":"This first section of the cookbook aims at providing the reader with an introduction to ","position":{"start":{"line":3,"column":1},"end":{"line":3,"column":1}},"key":"rhzJmA8Jr0"},{"type":"link","url":"https://healpix.sourceforge.io/","position":{"start":{"line":3,"column":1},"end":{"line":3,"column":1}},"children":[{"type":"strong","position":{"start":{"line":3,"column":1},"end":{"line":3,"column":1}},"children":[{"type":"text","value":"H","position":{"start":{"line":3,"column":1},"end":{"line":3,"column":1}},"key":"Xh4boGjAWS"}],"key":"c9ayvTolFt"},{"type":"text","value":"ierarchical ","position":{"start":{"line":3,"column":1},"end":{"line":3,"column":1}},"key":"bSDlF1T2i5"},{"type":"strong","position":{"start":{"line":3,"column":1},"end":{"line":3,"column":1}},"children":[{"type":"text","value":"E","position":{"start":{"line":3,"column":1},"end":{"line":3,"column":1}},"key":"oDzjDqFPT3"}],"key":"lJp6t9eZac"},{"type":"text","value":"qual ","position":{"start":{"line":3,"column":1},"end":{"line":3,"column":1}},"key":"cWuT9gOWqq"},{"type":"strong","position":{"start":{"line":3,"column":1},"end":{"line":3,"column":1}},"children":[{"type":"text","value":"A","position":{"start":{"line":3,"column":1},"end":{"line":3,"column":1}},"key":"L9RUMsQ2Qt"}],"key":"kFBH92H4WE"},{"type":"text","value":"rea iso","position":{"start":{"line":3,"column":1},"end":{"line":3,"column":1}},"key":"lm8ABR92zf"},{"type":"strong","position":{"start":{"line":3,"column":1},"end":{"line":3,"column":1}},"children":[{"type":"text","value":"L","position":{"start":{"line":3,"column":1},"end":{"line":3,"column":1}},"key":"tW5SVcx6sP"}],"key":"OOZLZaABOE"},{"type":"text","value":"atitude ","position":{"start":{"line":3,"column":1},"end":{"line":3,"column":1}},"key":"OkXzw14kGj"},{"type":"strong","position":{"start":{"line":3,"column":1},"end":{"line":3,"column":1}},"children":[{"type":"text","value":"Pix","position":{"start":{"line":3,"column":1},"end":{"line":3,"column":1}},"key":"DJc1UoGw5p"}],"key":"ZZY1Fb4trx"},{"type":"text","value":"elation (HEALPix)","position":{"start":{"line":3,"column":1},"end":{"line":3,"column":1}},"key":"exnSTf4FoG"}],"urlSource":"https://healpix.sourceforge.io/","key":"V5cAF8uc31"},{"type":"text","value":". However, rather than duplicating tons of information that is already available at HEALPix resources, we will try guiding the Pythia’s community in the right direction to access those resources.","position":{"start":{"line":3,"column":1},"end":{"line":3,"column":1}},"key":"o1Eda1GtQc"}],"key":"Gyz73HPbB9"},{"type":"heading","depth":3,"position":{"start":{"line":5,"column":1},"end":{"line":5,"column":1}},"children":[{"type":"text","value":"In this section, you’ll learn:","position":{"start":{"line":5,"column":1},"end":{"line":5,"column":1}},"key":"WETAGIpgq3"}],"identifier":"in-this-section-youll-learn","label":"In this section, you’ll learn:","html_id":"in-this-section-youll-learn","implicit":true,"key":"QzC6bbOTNV"},{"type":"list","ordered":false,"spread":false,"position":{"start":{"line":7,"column":1},"end":{"line":10,"column":1}},"children":[{"type":"listItem","spread":true,"position":{"start":{"line":7,"column":1},"end":{"line":7,"column":1}},"children":[{"type":"text","value":"What is HEALPix?","position":{"start":{"line":7,"column":1},"end":{"line":7,"column":1}},"key":"vWrGMmwyhG"}],"key":"KFWK2nuzum"},{"type":"listItem","spread":true,"position":{"start":{"line":8,"column":1},"end":{"line":8,"column":1}},"children":[{"type":"text","value":"What resources can lead you to learn more about HEALPix?","position":{"start":{"line":8,"column":1},"end":{"line":8,"column":1}},"key":"lmqYUbTjFH"}],"key":"EZ817Axky6"},{"type":"listItem","spread":true,"position":{"start":{"line":9,"column":1},"end":{"line":10,"column":1}},"children":[{"type":"text","value":"Why HEALPix?","position":{"start":{"line":9,"column":1},"end":{"line":9,"column":1}},"key":"KXaisULGtV"}],"key":"fdkf6uKAXl"}],"key":"qwGtPGIZsy"},{"type":"heading","depth":3,"position":{"start":{"line":11,"column":1},"end":{"line":11,"column":1}},"children":[{"type":"text","value":"Related Documentation","position":{"start":{"line":11,"column":1},"end":{"line":11,"column":1}},"key":"AyYYKQqXm8"}],"identifier":"related-documentation","label":"Related Documentation","html_id":"related-documentation","implicit":true,"key":"wuZ8OwCYOr"},{"type":"list","ordered":false,"spread":false,"position":{"start":{"line":13,"column":1},"end":{"line":17,"column":1}},"children":[{"type":"listItem","spread":true,"position":{"start":{"line":13,"column":1},"end":{"line":13,"column":1}},"children":[{"type":"link","url":"https://healpix.sourceforge.io/","position":{"start":{"line":13,"column":1},"end":{"line":13,"column":1}},"children":[{"type":"text","value":"HEALPix Homepage","position":{"start":{"line":13,"column":1},"end":{"line":13,"column":1}},"key":"flKV7SRAFs"}],"urlSource":"https://healpix.sourceforge.io/","key":"Bl95BqZxXa"}],"key":"Pvj5BXB6Bv"},{"type":"listItem","spread":true,"position":{"start":{"line":14,"column":1},"end":{"line":14,"column":1}},"children":[{"type":"link","url":"https://healpix.sourceforge.io/documentation.php","position":{"start":{"line":14,"column":1},"end":{"line":14,"column":1}},"children":[{"type":"text","value":"HEALPix Documentation","position":{"start":{"line":14,"column":1},"end":{"line":14,"column":1}},"key":"xSYj54c8Xp"}],"urlSource":"https://healpix.sourceforge.io/documentation.php","key":"Hxt1QOUq1r"}],"key":"gQt8lUlqfR"},{"type":"listItem","spread":true,"position":{"start":{"line":15,"column":1},"end":{"line":15,"column":1}},"children":[{"type":"link","url":"https://healpix.sourceforge.io/resources.php","position":{"start":{"line":15,"column":1},"end":{"line":15,"column":1}},"children":[{"type":"text","value":"HEALPix Resources","position":{"start":{"line":15,"column":1},"end":{"line":15,"column":1}},"key":"qqStvQSbFO"}],"urlSource":"https://healpix.sourceforge.io/resources.php","key":"q1kHu3M830"}],"key":"GWKnBrqHPN"},{"type":"listItem","spread":true,"position":{"start":{"line":16,"column":1},"end":{"line":17,"column":1}},"children":[{"type":"link","url":"https://healpix.sourceforge.io/support.php","position":{"start":{"line":16,"column":1},"end":{"line":16,"column":1}},"children":[{"type":"text","value":"HEALPix Support","position":{"start":{"line":16,"column":1},"end":{"line":16,"column":1}},"key":"YL746CY9ma"}],"urlSource":"https://healpix.sourceforge.io/support.php","key":"Z1LWZqrpxZ"}],"key":"n0449GfShS"}],"key":"FGww6gEHo4"},{"type":"heading","depth":3,"position":{"start":{"line":18,"column":1},"end":{"line":18,"column":1}},"children":[{"type":"text","value":"Prerequisites","position":{"start":{"line":18,"column":1},"end":{"line":18,"column":1}},"key":"PVA4gdQd5m"}],"identifier":"prerequisites","label":"Prerequisites","html_id":"prerequisites","implicit":true,"key":"pIz1I6ZdrH"},{"type":"table","position":{"start":{"line":20,"column":1},"end":{"line":22,"column":1}},"children":[{"type":"tableRow","position":{"start":{"line":20,"column":1},"end":{"line":20,"column":1}},"children":[{"type":"tableCell","header":true,"position":{"start":{"line":20,"column":1},"end":{"line":20,"column":1}},"children":[{"type":"text","value":"Concepts","position":{"start":{"line":20,"column":1},"end":{"line":20,"column":1}},"key":"St7VyWeA5p"}],"key":"reXwv82l0p"},{"type":"tableCell","header":true,"position":{"start":{"line":20,"column":1},"end":{"line":20,"column":1}},"children":[{"type":"text","value":"Importance","position":{"start":{"line":20,"column":1},"end":{"line":20,"column":1}},"key":"eQBoBRlb4o"}],"key":"C5tT3CIt6K"},{"type":"tableCell","header":true,"position":{"start":{"line":20,"column":1},"end":{"line":20,"column":1}},"children":[{"type":"text","value":"Notes","position":{"start":{"line":20,"column":1},"end":{"line":20,"column":1}},"key":"R1ijDu2Myc"}],"key":"VIsznnIpQ1"}],"key":"x3n1LyyqSZ"},{"type":"tableRow","position":{"start":{"line":22,"column":1},"end":{"line":22,"column":1}},"children":[{"type":"tableCell","position":{"start":{"line":22,"column":1},"end":{"line":22,"column":1}},"children":[{"type":"cite","url":"https://doi.org/10.1002/9781118786352.wbieg1050","position":{"start":{"line":22,"column":1},"end":{"line":22,"column":1}},"children":[{"type":"text","value":"Discrete Global Grid Systems","position":{"start":{"line":22,"column":1},"end":{"line":22,"column":1}},"key":"zlhcM85S7c"}],"kind":"narrative","label":"Peterson_2017","identifier":"https://doi.org/10.1002/9781118786352.wbieg1050","enumerator":"1","key":"AmWxLd2ZIw"}],"key":"DOwXoB4Q3y"},{"type":"tableCell","position":{"start":{"line":22,"column":1},"end":{"line":22,"column":1}},"children":[{"type":"text","value":"Helpful","position":{"start":{"line":22,"column":1},"end":{"line":22,"column":1}},"key":"xxcWs0rguJ"}],"key":"RRT28SOJ4u"},{"type":"tableCell","position":{"start":{"line":22,"column":1},"end":{"line":22,"column":1}},"children":[],"key":"MOUtvaibuk"}],"key":"xNVR7Z1doH"}],"key":"AvKZ44RBEi"},{"type":"paragraph","position":{"start":{"line":24,"column":1},"end":{"line":24,"column":1}},"children":[{"type":"strong","position":{"start":{"line":24,"column":1},"end":{"line":24,"column":1}},"children":[{"type":"text","value":"Time to learn","position":{"start":{"line":24,"column":1},"end":{"line":24,"column":1}},"key":"bETefRp0Uc"}],"key":"CEOGmCHHfI"},{"type":"text","value":": 10 minutes","position":{"start":{"line":24,"column":1},"end":{"line":24,"column":1}},"key":"NxO5fHS9s9"}],"key":"QHhtEOCIn5"},{"type":"thematicBreak","position":{"start":{"line":26,"column":1},"end":{"line":26,"column":1}},"key":"RY9jED26oW"}],"key":"Gnw2UbMCD2"},{"type":"block","kind":"notebook-content","children":[{"type":"heading","depth":2,"position":{"start":{"line":1,"column":1},"end":{"line":1,"column":1}},"children":[{"type":"text","value":"What is HEALPix?","position":{"start":{"line":1,"column":1},"end":{"line":1,"column":1}},"key":"AwTqcLT8Ka"}],"identifier":"what-is-healpix","label":"What is HEALPix?","html_id":"what-is-healpix","implicit":true,"key":"veWIJZpn6B"}],"key":"ZMtbnYtaNH"},{"type":"block","kind":"notebook-content","children":[{"type":"paragraph","position":{"start":{"line":1,"column":1},"end":{"line":1,"column":1}},"children":[{"type":"text","value":"HEALPix is a high resolution discretization framework to provide equal area, iso-Latitude pixelation of a sphere for fast analysis of data distributed on it, which produces a subdivision of the spherical surface in which each pixel covers the same surface area as every other pixel at a given resolution level.","position":{"start":{"line":1,"column":1},"end":{"line":1,"column":1}},"key":"nF7uLYJesV"}],"key":"y6Y1goUyE8"},{"type":"paragraph","position":{"start":{"line":3,"column":1},"end":{"line":3,"column":1}},"children":[{"type":"text","value":"HEALPix was originally devised to support fast and accurate mathematical calculations on a spherical discretization at sufficiently high resolution levels for satellite missions to measure the cosmic microwave background (CMB), and it has later been adopted to geoscience applications as well.","position":{"start":{"line":3,"column":1},"end":{"line":3,"column":1}},"key":"pFnJl9Joos"}],"key":"AWlr6guj8k"},{"type":"paragraph","position":{"start":{"line":5,"column":1},"end":{"line":5,"column":1}},"children":[{"type":"text","value":"Be sure to check out the ","position":{"start":{"line":5,"column":1},"end":{"line":5,"column":1}},"key":"jYb3t4HtcH"},{"type":"link","url":"https://healpix.sourceforge.io/index.php","position":{"start":{"line":5,"column":1},"end":{"line":5,"column":1}},"children":[{"type":"text","value":"HEALPix home page","position":{"start":{"line":5,"column":1},"end":{"line":5,"column":1}},"key":"ieyNUNMiRo"}],"urlSource":"https://healpix.sourceforge.io/index.php","key":"wVdj5dyxhN"},{"type":"text","value":" and the References at the end of this section for further details.","position":{"start":{"line":5,"column":1},"end":{"line":5,"column":1}},"key":"njhBJq18ns"}],"key":"zvaES3oYKK"},{"type":"paragraph","position":{"start":{"line":7,"column":1},"end":{"line":10,"column":1}},"children":[{"type":"image","url":"/healpix-cookbook/build/905fe1ae8d9a0e41b8fe13928c963fdd.jpeg","alt":"Matplotlib Logo","width":250,"key":"VHuzjiZo9Q","urlSource":"https://healpix.sourceforge.io/images/gorski_f1.jpg"}],"key":"J3auJj86iH"}],"key":"tGRclTFWZ2"},{"type":"block","kind":"notebook-content","children":[{"type":"heading","depth":2,"position":{"start":{"line":1,"column":1},"end":{"line":1,"column":1}},"children":[{"type":"text","value":"Why HEALPix?","position":{"start":{"line":1,"column":1},"end":{"line":1,"column":1}},"key":"R0NjNcn1nb"}],"identifier":"why-healpix","label":"Why HEALPix?","html_id":"why-healpix","implicit":true,"key":"PPIHDUEzCR"}],"key":"wLF6OfQPfn"},{"type":"block","kind":"notebook-content","children":[{"type":"paragraph","position":{"start":{"line":1,"column":1},"end":{"line":1,"column":1}},"children":[{"type":"text","value":"Three key features of HEALPix are:","position":{"start":{"line":1,"column":1},"end":{"line":1,"column":1}},"key":"imQuGTdtx4"}],"key":"RMHnyb6n7r"},{"type":"list","ordered":false,"spread":false,"position":{"start":{"line":3,"column":1},"end":{"line":6,"column":1}},"children":[{"type":"listItem","spread":true,"position":{"start":{"line":3,"column":1},"end":{"line":3,"column":1}},"children":[{"type":"text","value":"The sphere is hierarchically tessellated into curvilinear quadrilaterals","position":{"start":{"line":3,"column":1},"end":{"line":3,"column":1}},"key":"sGaivYUYXd"}],"key":"PAIA8azV4H"},{"type":"listItem","spread":true,"position":{"start":{"line":4,"column":1},"end":{"line":4,"column":1}},"children":[{"type":"text","value":"Areas of all pixels at a given resolution are identical","position":{"start":{"line":4,"column":1},"end":{"line":4,"column":1}},"key":"u6aZs3AByF"}],"key":"eFrVTNKqQV"},{"type":"listItem","spread":true,"position":{"start":{"line":5,"column":1},"end":{"line":6,"column":1}},"children":[{"type":"text","value":"Pixels are distributed on lines of constant latitude","position":{"start":{"line":5,"column":1},"end":{"line":5,"column":1}},"key":"WIPopp3RQL"}],"key":"UDicTYKt4J"}],"key":"venubri6Yh"},{"type":"paragraph","position":{"start":{"line":7,"column":1},"end":{"line":7,"column":1}},"children":[{"type":"text","value":"These properties make HEALPix a good gridding choice to facilitate fast and accurate statistical and spherical analysis for high-resolution data such as spherical harmonics.","position":{"start":{"line":7,"column":1},"end":{"line":7,"column":1}},"key":"vZtQiibo1d"}],"key":"Rh3HpR0TvE"}],"key":"atcSbCk4Sl"},{"type":"block","kind":"notebook-content","children":[{"type":"heading","depth":2,"position":{"start":{"line":1,"column":1},"end":{"line":1,"column":1}},"children":[{"type":"text","value":"Where to learn more about HEALPix?","position":{"start":{"line":1,"column":1},"end":{"line":1,"column":1}},"key":"xyaH1gCk7X"}],"identifier":"where-to-learn-more-about-healpix","label":"Where to learn more about HEALPix?","html_id":"where-to-learn-more-about-healpix","implicit":true,"key":"EGJak8TB2B"}],"key":"K50RwU5z9k"},{"type":"block","kind":"notebook-content","children":[{"type":"paragraph","position":{"start":{"line":1,"column":1},"end":{"line":1,"column":1}},"children":[{"type":"text","value":"In addition to the ","position":{"start":{"line":1,"column":1},"end":{"line":1,"column":1}},"key":"aL9DE1BVUl"},{"type":"crossReference","position":{"start":{"line":1,"column":1},"end":{"line":1,"column":1}},"children":[{"type":"text","value":"Related Documentation","position":{"start":{"line":1,"column":1},"end":{"line":1,"column":1}},"key":"OVGaTTWlCW"}],"identifier":"related-documentation","label":"related-documentation","kind":"heading","template":"{name}","resolved":true,"html_id":"related-documentation","key":"yk1X7Ydh8O"},{"type":"text","value":" provided in the beginning of this notebook, there are some good resources that you can further learn HEALPix through. In this part, we’d like to introduce one of them, easy.gems:","position":{"start":{"line":1,"column":1},"end":{"line":1,"column":1}},"key":"GwUrCWKGhn"}],"key":"QwACsQf55E"}],"key":"gkosuZu6q2"},{"type":"block","kind":"notebook-content","children":[{"type":"heading","depth":3,"position":{"start":{"line":1,"column":1},"end":{"line":1,"column":1}},"children":[{"type":"text","value":"easy.gems","position":{"start":{"line":1,"column":1},"end":{"line":1,"column":1}},"key":"WQfqoihCmU"}],"identifier":"easy-gems","label":"easy.gems","html_id":"easy-gems","implicit":true,"key":"UwOkDTd8WN"},{"type":"paragraph","position":{"start":{"line":3,"column":1},"end":{"line":3,"column":1}},"children":[{"type":"link","url":"https://www.dkrz.de/en","position":{"start":{"line":3,"column":1},"end":{"line":3,"column":1}},"children":[{"type":"text","value":"DKRZ (The German Climate Computing Center)","position":{"start":{"line":3,"column":1},"end":{"line":3,"column":1}},"key":"HChdcvlHOD"}],"urlSource":"https://www.dkrz.de/en","key":"aiz4U73xaO"},{"type":"text","value":" created ","position":{"start":{"line":3,"column":1},"end":{"line":3,"column":1}},"key":"lGz3yQLR2w"},{"type":"link","url":"https://easy.gems.dkrz.de/index.html","position":{"start":{"line":3,"column":1},"end":{"line":3,"column":1}},"children":[{"type":"text","value":"easy.gems","position":{"start":{"line":3,"column":1},"end":{"line":3,"column":1}},"key":"CkiXRcyy2W"}],"urlSource":"https://easy.gems.dkrz.de/index.html","key":"L3N0C76Cws"},{"type":"text","value":" for documenting high-resolution climate simulation output and its analysis, which was started within the frame of the ","position":{"start":{"line":3,"column":1},"end":{"line":3,"column":1}},"key":"eD7vowZXqz"},{"type":"link","url":"https://www.esiwace.eu/the-project/past-phases/dyamond-initiative","position":{"start":{"line":3,"column":1},"end":{"line":3,"column":1}},"children":[{"type":"text","value":"DYAMOND intercomparison initiative","position":{"start":{"line":3,"column":1},"end":{"line":3,"column":1}},"key":"riQTzbJf3I"}],"urlSource":"https://www.esiwace.eu/the-project/past-phases/dyamond-initiative","key":"cOYxQutCv8"},{"type":"text","value":".","position":{"start":{"line":3,"column":1},"end":{"line":3,"column":1}},"key":"hh6hTGgAWp"}],"key":"dQEqvRPb3K"},{"type":"paragraph","position":{"start":{"line":5,"column":1},"end":{"line":5,"column":1}},"children":[{"type":"text","value":"Since output in multiple resolutions (hierarchical) is written on the HEALPix grid in order to simplify and speed up analysis, easy.gems provides ","position":{"start":{"line":5,"column":1},"end":{"line":5,"column":1}},"key":"z4kIpCoHc7"},{"type":"link","url":"https://easy.gems.dkrz.de/Processing/healpix/index.html#","position":{"start":{"line":5,"column":1},"end":{"line":5,"column":1}},"children":[{"type":"text","value":"documentation","position":{"start":{"line":5,"column":1},"end":{"line":5,"column":1}},"key":"nmYx6cD74V"}],"urlSource":"https://easy.gems.dkrz.de/Processing/healpix/index.html#","key":"nCxGI6Ricc"},{"type":"text","value":" for a range of applications such as getting started with HEALPix, using HEALPix analysis and plotting functionality on the simulation data, and performing conversions between HEALPix and other grid types.","position":{"start":{"line":5,"column":1},"end":{"line":5,"column":1}},"key":"dxCYz7zHtT"}],"key":"KZvjDPSvyr"},{"type":"paragraph","position":{"start":{"line":7,"column":1},"end":{"line":7,"column":1}},"children":[{"type":"text","value":"The ","position":{"start":{"line":7,"column":1},"end":{"line":7,"column":1}},"key":"ewY745sQCS"},{"type":"link","url":"/notebooks/easygems","position":{"start":{"line":7,"column":1},"end":{"line":7,"column":1}},"children":[{"type":"text","value":"next section","position":{"start":{"line":7,"column":1},"end":{"line":7,"column":1}},"key":"wRNMpnJU6s"}],"urlSource":"01-easygems","dataUrl":"/notebooks.easygems.json","internal":true,"protocol":"file","key":"DTdZnJFbUk"},{"type":"text","value":" will showcase an easy.gems workflow that loads in, manipulates, analyzes, and visualizes HEALpix data, which uses easy.gems functions and other scientific Python ecosystem packages’ functionality recommended by easy.gems.","position":{"start":{"line":7,"column":1},"end":{"line":7,"column":1}},"key":"mRRSJNdDrX"}],"key":"AykOQC9m2h"}],"key":"URcMw2oCxg"},{"type":"block","kind":"notebook-content","children":[{"type":"heading","depth":2,"position":{"start":{"line":1,"column":1},"end":{"line":1,"column":1}},"children":[{"type":"text","value":"References","position":{"start":{"line":1,"column":1},"end":{"line":1,"column":1}},"key":"mAYUP4Zssk"}],"identifier":"references","label":"References","html_id":"references","implicit":true,"key":"EPXxPmqnon"},{"type":"paragraph","position":{"start":{"line":3,"column":1},"end":{"line":3,"column":1}},"children":[{"type":"cite","url":"https://iopscience.iop.org/article/10.1086/427976/meta","position":{"start":{"line":3,"column":1},"end":{"line":3,"column":1}},"children":[{"type":"text","value":"Gorski et al. 2005 “HEALPix: A framework for high-resolution discretization and fast analysis of data distributed on the sphere”","position":{"start":{"line":3,"column":1},"end":{"line":3,"column":1}},"key":"kJQuDaX7fb"}],"kind":"narrative","label":"Gorski_2005","identifier":"https://iopscience.iop.org/article/10.1086/427976/meta","enumerator":"2","key":"yZRAuIejjU"}],"key":"HUFb9gHlY7"},{"type":"paragraph","position":{"start":{"line":5,"column":1},"end":{"line":5,"column":1}},"children":[{"type":"cite","url":"https://doi.org/10.1002/9781118786352.wbieg1050","position":{"start":{"line":5,"column":1},"end":{"line":5,"column":1}},"children":[{"type":"text","value":"Peterson et al. 2016 “Discrete global grid systems”","position":{"start":{"line":5,"column":1},"end":{"line":5,"column":1}},"key":"gQF65fjs5y"}],"kind":"narrative","label":"Peterson_2017","identifier":"https://doi.org/10.1002/9781118786352.wbieg1050","enumerator":"1","key":"urvQ75HrP0"}],"key":"uJsDYAgj69"}],"key":"Mx6zdKVEfe"},{"type":"block","kind":"notebook-content","children":[{"type":"heading","depth":2,"position":{"start":{"line":1,"column":1},"end":{"line":1,"column":1}},"children":[{"type":"text","value":"What is next?","position":{"start":{"line":1,"column":1},"end":{"line":1,"column":1}},"key":"eagHVI0ueo"}],"identifier":"what-is-next","label":"What is next?","html_id":"what-is-next","implicit":true,"key":"deCaSEA1SN"},{"type":"paragraph","position":{"start":{"line":3,"column":1},"end":{"line":3,"column":1}},"children":[{"type":"text","value":"The ","position":{"start":{"line":3,"column":1},"end":{"line":3,"column":1}},"key":"f7vF4Kvb5K"},{"type":"link","url":"/notebooks/easygems","position":{"start":{"line":3,"column":1},"end":{"line":3,"column":1}},"children":[{"type":"text","value":"next section","position":{"start":{"line":3,"column":1},"end":{"line":3,"column":1}},"key":"s6uqfKNr4f"}],"urlSource":"01-easygems","dataUrl":"/notebooks.easygems.json","internal":true,"protocol":"file","key":"tDI5MYUrZI"},{"type":"text","value":" will provide an easy.gems workflow that uses HEALPix data.","position":{"start":{"line":3,"column":1},"end":{"line":3,"column":1}},"key":"NXrJsRPLoC"}],"key":"N718d4Loto"}],"key":"rPp0b8tWRs"}],"key":"B52lHP75IK"},"references":{"cite":{"order":["Peterson_2017","Gorski_2005"],"data":{"Peterson_2017":{"label":"Peterson_2017","enumerator":"1","doi":"10.1002/9781118786352.wbieg1050","html":"Peterson, P. R. (2017). Discrete Global Grid Systems. In <i>International Encyclopedia of Geography</i> (pp. 1–10). Wiley. <a target=\"_blank\" rel=\"noreferrer\" href=\"https://doi.org/10.1002/9781118786352.wbieg1050\">10.1002/9781118786352.wbieg1050</a>","url":"https://doi.org/10.1002/9781118786352.wbieg1050"},"Gorski_2005":{"label":"Gorski_2005","enumerator":"2","doi":"10.1086/427976","html":"Gorski, K. M., Hivon, E., Banday, A. J., Wandelt, B. D., Hansen, F. K., Reinecke, M., & Bartelmann, M. (2005). HEALPix: A Framework for High‐Resolution Discretization and Fast Analysis of Data Distributed on the Sphere. <i>The Astrophysical Journal</i>, <i>622</i>(2), 759–771. <a target=\"_blank\" rel=\"noreferrer\" href=\"https://doi.org/10.1086/427976\">10.1086/427976</a>","url":"https://doi.org/10.1086/427976"}}}},"footer":{"navigation":{"prev":{"title":"How to Cite This Cookbook","url":"/notebooks/how-to-cite","group":"Preamble"},"next":{"title":"easy.gems for HEALPix Analysis & Visualization","url":"/notebooks/easygems","group":"HEALPix Analysis & Visualization"}}},"domain":"http://localhost:3000"}