{"version":2,"kind":"Notebook","sha256":"26b8067b96f2418bf8db2e802a7820773ed89f3eb404d41d1c6058b0f66ae36d","slug":"notebooks.healpix","location":"/notebooks/00-healpix.ipynb","dependencies":[],"frontmatter":{"title":"HEALPix Overview","content_includes_title":false,"kernelspec":{"name":"python3","display_name":"Python 3 (ipykernel)","language":"python"},"authors":[{"nameParsed":{"literal":"Project Pythia Community","given":"Project Pythia","family":"Community"},"name":"Project Pythia Community","url":"https://projectpythia.org/","id":"contributors-myst-generated-uid-0"}],"open_access":true,"license":{"content":{"id":"CC-BY-4.0","url":"https://creativecommons.org/licenses/by/4.0/","name":"Creative Commons Attribution 4.0 International","free":true,"CC":true},"code":{"id":"Apache-2.0","url":"https://opensource.org/licenses/Apache-2.0","name":"Apache License 2.0","free":true,"osi":true}},"github":"https://github.com/projectpythia/healpix-cookbook","copyright":"2025","affiliations":[{"id":"UAlbany","name":"University at Albany (SUNY)","department":"Atmospheric and Environmental Sciences","url":"https://www.albany.edu/daes"},{"id":"CISL","name":"NSF National Center for Atmospheric Research","department":"Computational and Information Systems Lab","url":"https://www.cisl.ucar.edu"},{"id":"Unidata","name":"NSF Unidata","url":"https://www.unidata.ucar.edu"},{"id":"Argonne","name":"Argonne National Laboratory","department":"Environmental Science Division","url":"https://www.anl.gov/evs"},{"id":"CarbonPlan","name":"CarbonPlan","url":"https://carbonplan.org"},{"id":"NVIDIA","name":"NVIDIA Corporation","url":"https://www.nvidia.com/"}],"numbering":{"title":{"offset":1}},"source_url":"https://github.com/projectpythia/healpix-cookbook/blob/main/notebooks/00-healpix.ipynb","edit_url":"https://github.com/projectpythia/healpix-cookbook/edit/main/notebooks/00-healpix.ipynb","thumbnail":"/healpix-cookbook/build/905fe1ae8d9a0e41b8fe13928c963fdd.jpeg","exports":[{"format":"ipynb","filename":"00-healpix.ipynb","url":"/healpix-cookbook/build/00-healpix-2871d8822cbb0ed2e8b0fbb82de5c794.ipynb"}]},"widgets":{},"mdast":{"type":"root","children":[{"type":"block","kind":"notebook-content","children":[{"type":"paragraph","position":{"start":{"line":3,"column":1},"end":{"line":3,"column":1}},"children":[{"type":"text","value":"This first section of the cookbook aims at providing the reader with an introduction to ","position":{"start":{"line":3,"column":1},"end":{"line":3,"column":1}},"key":"UazxR7JJlo"},{"type":"link","url":"https://healpix.sourceforge.io/","position":{"start":{"line":3,"column":1},"end":{"line":3,"column":1}},"children":[{"type":"strong","position":{"start":{"line":3,"column":1},"end":{"line":3,"column":1}},"children":[{"type":"text","value":"H","position":{"start":{"line":3,"column":1},"end":{"line":3,"column":1}},"key":"b1HWiI6Ndm"}],"key":"q2m2d8k6ro"},{"type":"text","value":"ierarchical ","position":{"start":{"line":3,"column":1},"end":{"line":3,"column":1}},"key":"gzDiBS66Ly"},{"type":"strong","position":{"start":{"line":3,"column":1},"end":{"line":3,"column":1}},"children":[{"type":"text","value":"E","position":{"start":{"line":3,"column":1},"end":{"line":3,"column":1}},"key":"GG7A2sEMGf"}],"key":"vhRv9bfWGG"},{"type":"text","value":"qual ","position":{"start":{"line":3,"column":1},"end":{"line":3,"column":1}},"key":"LdueLDzrfn"},{"type":"strong","position":{"start":{"line":3,"column":1},"end":{"line":3,"column":1}},"children":[{"type":"text","value":"A","position":{"start":{"line":3,"column":1},"end":{"line":3,"column":1}},"key":"hBA0UoXxUI"}],"key":"gDJigH0a2E"},{"type":"text","value":"rea iso","position":{"start":{"line":3,"column":1},"end":{"line":3,"column":1}},"key":"ZQBoHJifmg"},{"type":"strong","position":{"start":{"line":3,"column":1},"end":{"line":3,"column":1}},"children":[{"type":"text","value":"L","position":{"start":{"line":3,"column":1},"end":{"line":3,"column":1}},"key":"znUQ0DA7BQ"}],"key":"ln0bjtnL4t"},{"type":"text","value":"atitude ","position":{"start":{"line":3,"column":1},"end":{"line":3,"column":1}},"key":"wHE3V797Qy"},{"type":"strong","position":{"start":{"line":3,"column":1},"end":{"line":3,"column":1}},"children":[{"type":"text","value":"Pix","position":{"start":{"line":3,"column":1},"end":{"line":3,"column":1}},"key":"gs2dCH5YUJ"}],"key":"iebNQlyrpb"},{"type":"text","value":"elation (HEALPix)","position":{"start":{"line":3,"column":1},"end":{"line":3,"column":1}},"key":"HgY0bIbtKF"}],"urlSource":"https://healpix.sourceforge.io/","key":"u8OntA82y8"},{"type":"text","value":". However, rather than duplicating tons of information that is already available at HEALPix resources, we will try guiding the Pythia’s community in the right direction to access those resources.","position":{"start":{"line":3,"column":1},"end":{"line":3,"column":1}},"key":"kdyOFnuvch"}],"key":"MIougYqRvv"},{"type":"heading","depth":3,"position":{"start":{"line":5,"column":1},"end":{"line":5,"column":1}},"children":[{"type":"text","value":"In this section, you’ll learn:","position":{"start":{"line":5,"column":1},"end":{"line":5,"column":1}},"key":"o3EA6AAF6Q"}],"identifier":"in-this-section-youll-learn","label":"In this section, you’ll learn:","html_id":"in-this-section-youll-learn","implicit":true,"key":"GxTV8gjHcX"},{"type":"list","ordered":false,"spread":false,"position":{"start":{"line":7,"column":1},"end":{"line":10,"column":1}},"children":[{"type":"listItem","spread":true,"position":{"start":{"line":7,"column":1},"end":{"line":7,"column":1}},"children":[{"type":"paragraph","children":[{"type":"text","value":"What is HEALPix?","position":{"start":{"line":7,"column":1},"end":{"line":7,"column":1}},"key":"ZXMa4RnxlB"}],"key":"f0FquM2Lxf"}],"key":"QFMRJirssK"},{"type":"listItem","spread":true,"position":{"start":{"line":8,"column":1},"end":{"line":8,"column":1}},"children":[{"type":"paragraph","children":[{"type":"text","value":"What resources can lead you to learn more about HEALPix?","position":{"start":{"line":8,"column":1},"end":{"line":8,"column":1}},"key":"YChUZHIitQ"}],"key":"HlxDg67Uuk"}],"key":"AlR63eBhI7"},{"type":"listItem","spread":true,"position":{"start":{"line":9,"column":1},"end":{"line":10,"column":1}},"children":[{"type":"paragraph","children":[{"type":"text","value":"Why HEALPix?","position":{"start":{"line":9,"column":1},"end":{"line":9,"column":1}},"key":"B7gW3mk7Zw"}],"key":"hSNzAvzbHT"}],"key":"os0zopv7pU"}],"key":"wp8QjKiN5E"},{"type":"heading","depth":3,"position":{"start":{"line":11,"column":1},"end":{"line":11,"column":1}},"children":[{"type":"text","value":"Related Documentation","position":{"start":{"line":11,"column":1},"end":{"line":11,"column":1}},"key":"MNuAW3aCeQ"}],"identifier":"related-documentation","label":"Related Documentation","html_id":"related-documentation","implicit":true,"key":"PcBdHPF2Ca"},{"type":"list","ordered":false,"spread":false,"position":{"start":{"line":13,"column":1},"end":{"line":17,"column":1}},"children":[{"type":"listItem","spread":true,"position":{"start":{"line":13,"column":1},"end":{"line":13,"column":1}},"children":[{"type":"paragraph","children":[{"type":"link","url":"https://healpix.sourceforge.io/","position":{"start":{"line":13,"column":1},"end":{"line":13,"column":1}},"children":[{"type":"text","value":"HEALPix Homepage","position":{"start":{"line":13,"column":1},"end":{"line":13,"column":1}},"key":"FioEthMIXU"}],"urlSource":"https://healpix.sourceforge.io/","key":"dhkqpg2N21"}],"key":"SPBWvR2sHG"}],"key":"OmX45NVHnY"},{"type":"listItem","spread":true,"position":{"start":{"line":14,"column":1},"end":{"line":14,"column":1}},"children":[{"type":"paragraph","children":[{"type":"link","url":"https://healpix.sourceforge.io/documentation.php","position":{"start":{"line":14,"column":1},"end":{"line":14,"column":1}},"children":[{"type":"text","value":"HEALPix Documentation","position":{"start":{"line":14,"column":1},"end":{"line":14,"column":1}},"key":"Sz38eNbTpS"}],"urlSource":"https://healpix.sourceforge.io/documentation.php","key":"yOkZPkQ5Yb"}],"key":"U5nJozPMCV"}],"key":"l59XQgVxo7"},{"type":"listItem","spread":true,"position":{"start":{"line":15,"column":1},"end":{"line":15,"column":1}},"children":[{"type":"paragraph","children":[{"type":"link","url":"https://healpix.sourceforge.io/resources.php","position":{"start":{"line":15,"column":1},"end":{"line":15,"column":1}},"children":[{"type":"text","value":"HEALPix Resources","position":{"start":{"line":15,"column":1},"end":{"line":15,"column":1}},"key":"CtlV84E09P"}],"urlSource":"https://healpix.sourceforge.io/resources.php","key":"HyUnBRkSjU"}],"key":"TCUkLCt2zo"}],"key":"euOKjiVqz6"},{"type":"listItem","spread":true,"position":{"start":{"line":16,"column":1},"end":{"line":17,"column":1}},"children":[{"type":"paragraph","children":[{"type":"link","url":"https://healpix.sourceforge.io/support.php","position":{"start":{"line":16,"column":1},"end":{"line":16,"column":1}},"children":[{"type":"text","value":"HEALPix Support","position":{"start":{"line":16,"column":1},"end":{"line":16,"column":1}},"key":"yAwov0XdEP"}],"urlSource":"https://healpix.sourceforge.io/support.php","key":"FENsGzr1ue"}],"key":"gncasbneSg"}],"key":"j4nSawsHmj"}],"key":"Gvdo60IZLC"},{"type":"heading","depth":3,"position":{"start":{"line":18,"column":1},"end":{"line":18,"column":1}},"children":[{"type":"text","value":"Prerequisites","position":{"start":{"line":18,"column":1},"end":{"line":18,"column":1}},"key":"ILwUV5yv5u"}],"identifier":"prerequisites","label":"Prerequisites","html_id":"prerequisites","implicit":true,"key":"py5E0Xlg4o"},{"type":"table","position":{"start":{"line":20,"column":1},"end":{"line":22,"column":1}},"children":[{"type":"tableRow","position":{"start":{"line":20,"column":1},"end":{"line":20,"column":1}},"children":[{"type":"tableCell","header":true,"position":{"start":{"line":20,"column":1},"end":{"line":20,"column":1}},"children":[{"type":"text","value":"Concepts","position":{"start":{"line":20,"column":1},"end":{"line":20,"column":1}},"key":"VLJ5JPF0Tc"}],"key":"jwBeQkPwIh"},{"type":"tableCell","header":true,"position":{"start":{"line":20,"column":1},"end":{"line":20,"column":1}},"children":[{"type":"text","value":"Importance","position":{"start":{"line":20,"column":1},"end":{"line":20,"column":1}},"key":"C9RVtH9X0v"}],"key":"EWDwVjob12"},{"type":"tableCell","header":true,"position":{"start":{"line":20,"column":1},"end":{"line":20,"column":1}},"children":[{"type":"text","value":"Notes","position":{"start":{"line":20,"column":1},"end":{"line":20,"column":1}},"key":"dZbKeh2uuK"}],"key":"CgQtZQdbXn"}],"key":"vUUI5ObXD0"},{"type":"tableRow","position":{"start":{"line":22,"column":1},"end":{"line":22,"column":1}},"children":[{"type":"tableCell","position":{"start":{"line":22,"column":1},"end":{"line":22,"column":1}},"children":[{"type":"cite","url":"https://doi.org/10.1002/9781118786352.wbieg1050","position":{"start":{"line":22,"column":1},"end":{"line":22,"column":1}},"children":[{"type":"text","value":"Discrete Global Grid Systems","position":{"start":{"line":22,"column":1},"end":{"line":22,"column":1}},"key":"QF9oRdhRKc"}],"kind":"narrative","label":"Peterson_2017","identifier":"https://doi.org/10.1002/9781118786352.wbieg1050","enumerator":"1","key":"qKGySzMsIx"}],"key":"A1E72spvVx"},{"type":"tableCell","position":{"start":{"line":22,"column":1},"end":{"line":22,"column":1}},"children":[{"type":"text","value":"Helpful","position":{"start":{"line":22,"column":1},"end":{"line":22,"column":1}},"key":"laGatVnQJ2"}],"key":"SPTYAaXbkv"},{"type":"tableCell","position":{"start":{"line":22,"column":1},"end":{"line":22,"column":1}},"children":[],"key":"gkF0yyjaGl"}],"key":"Wfyx5QyUeQ"}],"key":"yiuXSzqDkq"},{"type":"paragraph","position":{"start":{"line":24,"column":1},"end":{"line":24,"column":1}},"children":[{"type":"strong","position":{"start":{"line":24,"column":1},"end":{"line":24,"column":1}},"children":[{"type":"text","value":"Time to learn","position":{"start":{"line":24,"column":1},"end":{"line":24,"column":1}},"key":"H2F6m1P5Rd"}],"key":"AL4Bx3ovX6"},{"type":"text","value":": 10 minutes","position":{"start":{"line":24,"column":1},"end":{"line":24,"column":1}},"key":"jhBnvIVtGI"}],"key":"gwtEbtHTG5"},{"type":"thematicBreak","position":{"start":{"line":26,"column":1},"end":{"line":26,"column":1}},"key":"XydWXv8PPR"}],"key":"Cb8rmEyhdT"},{"type":"block","kind":"notebook-content","children":[{"type":"heading","depth":2,"position":{"start":{"line":1,"column":1},"end":{"line":1,"column":1}},"children":[{"type":"text","value":"What is HEALPix?","position":{"start":{"line":1,"column":1},"end":{"line":1,"column":1}},"key":"IjzPOKmGrw"}],"identifier":"what-is-healpix","label":"What is HEALPix?","html_id":"what-is-healpix","implicit":true,"key":"pLLtq9w2ZS"}],"key":"L8vxgB8OUW"},{"type":"block","kind":"notebook-content","children":[{"type":"paragraph","position":{"start":{"line":1,"column":1},"end":{"line":1,"column":1}},"children":[{"type":"text","value":"HEALPix is a high resolution discretization framework to provide equal area, iso-Latitude pixelation of a sphere for fast analysis of data distributed on it, which produces a subdivision of the spherical surface in which each pixel covers the same surface area as every other pixel at a given resolution level.","position":{"start":{"line":1,"column":1},"end":{"line":1,"column":1}},"key":"ls7doCrFkf"}],"key":"CBVJQieb9m"},{"type":"paragraph","position":{"start":{"line":3,"column":1},"end":{"line":3,"column":1}},"children":[{"type":"text","value":"HEALPix was originally devised to support fast and accurate mathematical calculations on a spherical discretization at sufficiently high resolution levels for satellite missions to measure the cosmic microwave background (CMB), and it has later been adopted to geoscience applications as well.","position":{"start":{"line":3,"column":1},"end":{"line":3,"column":1}},"key":"QESxtpU8DD"}],"key":"JbsZO0VifT"},{"type":"paragraph","position":{"start":{"line":5,"column":1},"end":{"line":5,"column":1}},"children":[{"type":"text","value":"Be sure to check out the ","position":{"start":{"line":5,"column":1},"end":{"line":5,"column":1}},"key":"w7oV932JOG"},{"type":"link","url":"https://healpix.sourceforge.io/index.php","position":{"start":{"line":5,"column":1},"end":{"line":5,"column":1}},"children":[{"type":"text","value":"HEALPix home page","position":{"start":{"line":5,"column":1},"end":{"line":5,"column":1}},"key":"AWNZcmigkY"}],"urlSource":"https://healpix.sourceforge.io/index.php","key":"p4bBw8NHph"},{"type":"text","value":" and the References at the end of this section for further details.","position":{"start":{"line":5,"column":1},"end":{"line":5,"column":1}},"key":"BI205zMTBU"}],"key":"ycg0PiHHpL"},{"type":"paragraph","position":{"start":{"line":7,"column":1},"end":{"line":10,"column":1}},"children":[{"type":"image","url":"/healpix-cookbook/build/905fe1ae8d9a0e41b8fe13928c963fdd.jpeg","alt":"Matplotlib Logo","width":250,"key":"hB2GjuQAVb","urlSource":"https://healpix.sourceforge.io/images/gorski_f1.jpg"}],"key":"dEK4MwQ2Nm"}],"key":"QY0bDm3WP2"},{"type":"block","kind":"notebook-content","children":[{"type":"heading","depth":2,"position":{"start":{"line":1,"column":1},"end":{"line":1,"column":1}},"children":[{"type":"text","value":"Why HEALPix?","position":{"start":{"line":1,"column":1},"end":{"line":1,"column":1}},"key":"Pcjy0ySc1X"}],"identifier":"why-healpix","label":"Why HEALPix?","html_id":"why-healpix","implicit":true,"key":"lDCG5zHrzK"}],"key":"GYDigIlmrB"},{"type":"block","kind":"notebook-content","children":[{"type":"paragraph","position":{"start":{"line":1,"column":1},"end":{"line":1,"column":1}},"children":[{"type":"text","value":"Three key features of HEALPix are:","position":{"start":{"line":1,"column":1},"end":{"line":1,"column":1}},"key":"S0oWR61fe7"}],"key":"SkTzcGp6F3"},{"type":"list","ordered":false,"spread":false,"position":{"start":{"line":3,"column":1},"end":{"line":6,"column":1}},"children":[{"type":"listItem","spread":true,"position":{"start":{"line":3,"column":1},"end":{"line":3,"column":1}},"children":[{"type":"paragraph","children":[{"type":"text","value":"The sphere is hierarchically tessellated into curvilinear quadrilaterals","position":{"start":{"line":3,"column":1},"end":{"line":3,"column":1}},"key":"IBgGiBsUbI"}],"key":"q92N2ni3B2"}],"key":"VNDa16rtVs"},{"type":"listItem","spread":true,"position":{"start":{"line":4,"column":1},"end":{"line":4,"column":1}},"children":[{"type":"paragraph","children":[{"type":"text","value":"Areas of all pixels at a given resolution are identical","position":{"start":{"line":4,"column":1},"end":{"line":4,"column":1}},"key":"E9XYx8Qtbn"}],"key":"RAFV8Tj285"}],"key":"Qg4xC7U7Lq"},{"type":"listItem","spread":true,"position":{"start":{"line":5,"column":1},"end":{"line":6,"column":1}},"children":[{"type":"paragraph","children":[{"type":"text","value":"Pixels are distributed on lines of constant latitude","position":{"start":{"line":5,"column":1},"end":{"line":5,"column":1}},"key":"k9ymrmbh1t"}],"key":"Gx2Yi0FvIG"}],"key":"hP6jedSpgI"}],"key":"aG2B5P8yxT"},{"type":"paragraph","position":{"start":{"line":7,"column":1},"end":{"line":7,"column":1}},"children":[{"type":"text","value":"These properties make HEALPix a good gridding choice to facilitate fast and accurate statistical and spherical analysis for high-resolution data such as spherical harmonics.","position":{"start":{"line":7,"column":1},"end":{"line":7,"column":1}},"key":"OsRlVNn6WO"}],"key":"F2iqtVIRMo"}],"key":"YhAkK4M2v4"},{"type":"block","kind":"notebook-content","children":[{"type":"heading","depth":2,"position":{"start":{"line":1,"column":1},"end":{"line":1,"column":1}},"children":[{"type":"text","value":"Where to learn more about HEALPix?","position":{"start":{"line":1,"column":1},"end":{"line":1,"column":1}},"key":"Q7vbXyYcDj"}],"identifier":"where-to-learn-more-about-healpix","label":"Where to learn more about HEALPix?","html_id":"where-to-learn-more-about-healpix","implicit":true,"key":"FZPoSFWfo6"}],"key":"CXN7hziOaS"},{"type":"block","kind":"notebook-content","children":[{"type":"paragraph","position":{"start":{"line":1,"column":1},"end":{"line":1,"column":1}},"children":[{"type":"text","value":"In addition to the ","position":{"start":{"line":1,"column":1},"end":{"line":1,"column":1}},"key":"FAW7J8zCOk"},{"type":"crossReference","position":{"start":{"line":1,"column":1},"end":{"line":1,"column":1}},"children":[{"type":"text","value":"Related Documentation","position":{"start":{"line":1,"column":1},"end":{"line":1,"column":1}},"key":"yycS8KNVQC"}],"identifier":"related-documentation","label":"related-documentation","kind":"heading","template":"{name}","resolved":true,"html_id":"related-documentation","key":"t1b6dRxgCd"},{"type":"text","value":" provided in the beginning of this notebook, there are some good resources that you can further learn HEALPix through. In this part, we’d like to introduce one of them, easy.gems:","position":{"start":{"line":1,"column":1},"end":{"line":1,"column":1}},"key":"v7OwAc7LbW"}],"key":"Hhtq3sp8en"}],"key":"S3BcWWP8p5"},{"type":"block","kind":"notebook-content","children":[{"type":"heading","depth":3,"position":{"start":{"line":1,"column":1},"end":{"line":1,"column":1}},"children":[{"type":"text","value":"easy.gems","position":{"start":{"line":1,"column":1},"end":{"line":1,"column":1}},"key":"bBzftmmYnx"}],"identifier":"easy-gems","label":"easy.gems","html_id":"easy-gems","implicit":true,"key":"oPAaB3JsqI"},{"type":"paragraph","position":{"start":{"line":3,"column":1},"end":{"line":3,"column":1}},"children":[{"type":"link","url":"https://www.dkrz.de/en","position":{"start":{"line":3,"column":1},"end":{"line":3,"column":1}},"children":[{"type":"text","value":"DKRZ (The German Climate Computing Center)","position":{"start":{"line":3,"column":1},"end":{"line":3,"column":1}},"key":"Pq56zp5aIG"}],"urlSource":"https://www.dkrz.de/en","key":"PheKzkgAcb"},{"type":"text","value":" created ","position":{"start":{"line":3,"column":1},"end":{"line":3,"column":1}},"key":"hFV5gchvlF"},{"type":"link","url":"https://easy.gems.dkrz.de/index.html","position":{"start":{"line":3,"column":1},"end":{"line":3,"column":1}},"children":[{"type":"text","value":"easy.gems","position":{"start":{"line":3,"column":1},"end":{"line":3,"column":1}},"key":"YKRbsAQ3P5"}],"urlSource":"https://easy.gems.dkrz.de/index.html","key":"YVSlb7Yl28"},{"type":"text","value":" for documenting high-resolution climate simulation output and its analysis, which was started within the frame of the ","position":{"start":{"line":3,"column":1},"end":{"line":3,"column":1}},"key":"fIpm3sDfjW"},{"type":"link","url":"https://www.esiwace.eu/the-project/past-phases/dyamond-initiative","position":{"start":{"line":3,"column":1},"end":{"line":3,"column":1}},"children":[{"type":"text","value":"DYAMOND intercomparison initiative","position":{"start":{"line":3,"column":1},"end":{"line":3,"column":1}},"key":"g0tH3f3qMq"}],"urlSource":"https://www.esiwace.eu/the-project/past-phases/dyamond-initiative","key":"UlELNXarYh"},{"type":"text","value":".","position":{"start":{"line":3,"column":1},"end":{"line":3,"column":1}},"key":"mdR75apQji"}],"key":"zUYhCUM5pM"},{"type":"paragraph","position":{"start":{"line":5,"column":1},"end":{"line":5,"column":1}},"children":[{"type":"text","value":"Since output in multiple resolutions (hierarchical) is written on the HEALPix grid in order to simplify and speed up analysis, easy.gems provides ","position":{"start":{"line":5,"column":1},"end":{"line":5,"column":1}},"key":"YiytcsZwns"},{"type":"link","url":"https://easy.gems.dkrz.de/Processing/healpix/index.html#","position":{"start":{"line":5,"column":1},"end":{"line":5,"column":1}},"children":[{"type":"text","value":"documentation","position":{"start":{"line":5,"column":1},"end":{"line":5,"column":1}},"key":"dqZQUC4ElW"}],"urlSource":"https://easy.gems.dkrz.de/Processing/healpix/index.html#","key":"EPuCljJJEt"},{"type":"text","value":" for a range of applications such as getting started with HEALPix, using HEALPix analysis and plotting functionality on the simulation data, and performing conversions between HEALPix and other grid types.","position":{"start":{"line":5,"column":1},"end":{"line":5,"column":1}},"key":"ec1J207nql"}],"key":"OY22FV5wg1"},{"type":"paragraph","position":{"start":{"line":7,"column":1},"end":{"line":7,"column":1}},"children":[{"type":"text","value":"The ","position":{"start":{"line":7,"column":1},"end":{"line":7,"column":1}},"key":"FvVb7jClxZ"},{"type":"link","url":"/notebooks/easygems","position":{"start":{"line":7,"column":1},"end":{"line":7,"column":1}},"children":[{"type":"text","value":"next section","position":{"start":{"line":7,"column":1},"end":{"line":7,"column":1}},"key":"AkrcSdpeND"}],"urlSource":"01-easygems","dataUrl":"/notebooks.easygems.json","internal":true,"protocol":"file","key":"O37Q8enZjs"},{"type":"text","value":" will showcase an easy.gems workflow that loads in, manipulates, analyzes, and visualizes HEALpix data, which uses easy.gems functions and other scientific Python ecosystem packages’ functionality recommended by easy.gems.","position":{"start":{"line":7,"column":1},"end":{"line":7,"column":1}},"key":"abNjQUFuBe"}],"key":"kLSKXaMFWv"}],"key":"hQ8Mve7y6s"},{"type":"block","kind":"notebook-content","children":[{"type":"heading","depth":2,"position":{"start":{"line":1,"column":1},"end":{"line":1,"column":1}},"children":[{"type":"text","value":"References","position":{"start":{"line":1,"column":1},"end":{"line":1,"column":1}},"key":"bya6Hu8LyF"}],"identifier":"references","label":"References","html_id":"references","implicit":true,"key":"NdAQI6x11t"},{"type":"paragraph","position":{"start":{"line":3,"column":1},"end":{"line":3,"column":1}},"children":[{"type":"cite","url":"https://iopscience.iop.org/article/10.1086/427976/meta","position":{"start":{"line":3,"column":1},"end":{"line":3,"column":1}},"children":[{"type":"text","value":"Gorski et al. 2005 “HEALPix: A framework for high-resolution discretization and fast analysis of data distributed on the sphere”","position":{"start":{"line":3,"column":1},"end":{"line":3,"column":1}},"key":"FVxVSpLML6"}],"kind":"narrative","label":"Gorski_2005","identifier":"https://iopscience.iop.org/article/10.1086/427976/meta","enumerator":"2","key":"smKmH7sMN9"}],"key":"STmFbrr9pB"},{"type":"paragraph","position":{"start":{"line":5,"column":1},"end":{"line":5,"column":1}},"children":[{"type":"cite","url":"https://doi.org/10.1002/9781118786352.wbieg1050","position":{"start":{"line":5,"column":1},"end":{"line":5,"column":1}},"children":[{"type":"text","value":"Peterson et al. 2016 “Discrete global grid systems”","position":{"start":{"line":5,"column":1},"end":{"line":5,"column":1}},"key":"GCknoafZ2n"}],"kind":"narrative","label":"Peterson_2017","identifier":"https://doi.org/10.1002/9781118786352.wbieg1050","enumerator":"1","key":"xaHaRtzvq8"}],"key":"yoENmKMO28"}],"key":"LEBa0WgRkc"},{"type":"block","kind":"notebook-content","children":[{"type":"heading","depth":2,"position":{"start":{"line":1,"column":1},"end":{"line":1,"column":1}},"children":[{"type":"text","value":"What is next?","position":{"start":{"line":1,"column":1},"end":{"line":1,"column":1}},"key":"vZdVudIOKQ"}],"identifier":"what-is-next","label":"What is next?","html_id":"what-is-next","implicit":true,"key":"lRWYr7kXK7"},{"type":"paragraph","position":{"start":{"line":3,"column":1},"end":{"line":3,"column":1}},"children":[{"type":"text","value":"The ","position":{"start":{"line":3,"column":1},"end":{"line":3,"column":1}},"key":"mjgHuF1RJ1"},{"type":"link","url":"/notebooks/easygems","position":{"start":{"line":3,"column":1},"end":{"line":3,"column":1}},"children":[{"type":"text","value":"next section","position":{"start":{"line":3,"column":1},"end":{"line":3,"column":1}},"key":"lUbtdDGrSI"}],"urlSource":"01-easygems","dataUrl":"/notebooks.easygems.json","internal":true,"protocol":"file","key":"vl1TMgkOH4"},{"type":"text","value":" will provide an easy.gems workflow that uses HEALPix data.","position":{"start":{"line":3,"column":1},"end":{"line":3,"column":1}},"key":"uCimUSnX2V"}],"key":"nfR8gKRIjg"}],"key":"YLJqiqE2YV"}],"key":"eujInjstHX"},"references":{"cite":{"order":["Peterson_2017","Gorski_2005"],"data":{"Peterson_2017":{"label":"Peterson_2017","enumerator":"1","doi":"10.1002/9781118786352.wbieg1050","html":"Peterson, P. R. (2017). Discrete Global Grid Systems. In <i>International Encyclopedia of Geography</i> (pp. 1–10). Wiley. <a target=\"_blank\" rel=\"noreferrer\" href=\"https://doi.org/10.1002/9781118786352.wbieg1050\">10.1002/9781118786352.wbieg1050</a>","url":"https://doi.org/10.1002/9781118786352.wbieg1050"},"Gorski_2005":{"label":"Gorski_2005","enumerator":"2","doi":"10.1086/427976","html":"Gorski, K. M., Hivon, E., Banday, A. J., Wandelt, B. D., Hansen, F. K., Reinecke, M., & Bartelmann, M. (2005). HEALPix: A Framework for High‐Resolution Discretization and Fast Analysis of Data Distributed on the Sphere. <i>The Astrophysical Journal</i>, <i>622</i>(2), 759–771. <a target=\"_blank\" rel=\"noreferrer\" href=\"https://doi.org/10.1086/427976\">10.1086/427976</a>","url":"https://doi.org/10.1086/427976"}}}},"footer":{"navigation":{"prev":{"title":"How to Cite This Cookbook","url":"/notebooks/how-to-cite","group":"Preamble"},"next":{"title":"easy.gems for HEALPix Analysis & Visualization","url":"/notebooks/easygems","group":"HEALPix Analysis & Visualization"}}},"domain":"http://localhost:3000"}