{"version":2,"kind":"Notebook","sha256":"26b8067b96f2418bf8db2e802a7820773ed89f3eb404d41d1c6058b0f66ae36d","slug":"notebooks.healpix","location":"/notebooks/00-healpix.ipynb","dependencies":[],"frontmatter":{"title":"HEALPix Overview","content_includes_title":false,"kernelspec":{"name":"python3","display_name":"Python 3 (ipykernel)","language":"python"},"authors":[{"nameParsed":{"literal":"Project Pythia Community","given":"Project Pythia","family":"Community"},"name":"Project Pythia Community","url":"https://projectpythia.org/","id":"contributors-myst-generated-uid-0"}],"open_access":true,"license":{"content":{"id":"CC-BY-4.0","url":"https://creativecommons.org/licenses/by/4.0/","name":"Creative Commons Attribution 4.0 International","free":true,"CC":true},"code":{"id":"Apache-2.0","url":"https://opensource.org/licenses/Apache-2.0","name":"Apache License 2.0","free":true,"osi":true}},"github":"https://github.com/projectpythia/healpix-cookbook","copyright":"2025","affiliations":[{"id":"UAlbany","name":"University at Albany (SUNY)","department":"Atmospheric and Environmental Sciences","url":"https://www.albany.edu/daes"},{"id":"CISL","name":"NSF National Center for Atmospheric Research","department":"Computational and Information Systems Lab","url":"https://www.cisl.ucar.edu"},{"id":"Unidata","name":"NSF Unidata","url":"https://www.unidata.ucar.edu"},{"id":"Argonne","name":"Argonne National Laboratory","department":"Environmental Science Division","url":"https://www.anl.gov/evs"},{"id":"CarbonPlan","name":"CarbonPlan","url":"https://carbonplan.org"},{"id":"NVIDIA","name":"NVIDIA Corporation","url":"https://www.nvidia.com/"}],"numbering":{"title":{"offset":1}},"source_url":"https://github.com/projectpythia/healpix-cookbook/blob/main/notebooks/00-healpix.ipynb","edit_url":"https://github.com/projectpythia/healpix-cookbook/edit/main/notebooks/00-healpix.ipynb","thumbnail":"/healpix-cookbook/build/905fe1ae8d9a0e41b8fe13928c963fdd.jpeg","exports":[{"format":"ipynb","filename":"00-healpix.ipynb","url":"/healpix-cookbook/build/00-healpix-faba52c40716723c94f686321531a27b.ipynb"}]},"widgets":{},"mdast":{"type":"root","children":[{"type":"block","kind":"notebook-content","children":[{"type":"paragraph","position":{"start":{"line":3,"column":1},"end":{"line":3,"column":1}},"children":[{"type":"text","value":"This first section of the cookbook aims at providing the reader with an introduction to ","position":{"start":{"line":3,"column":1},"end":{"line":3,"column":1}},"key":"aNnrsl8tOx"},{"type":"link","url":"https://healpix.sourceforge.io/","position":{"start":{"line":3,"column":1},"end":{"line":3,"column":1}},"children":[{"type":"strong","position":{"start":{"line":3,"column":1},"end":{"line":3,"column":1}},"children":[{"type":"text","value":"H","position":{"start":{"line":3,"column":1},"end":{"line":3,"column":1}},"key":"IROEHDgaNg"}],"key":"jqzn1kULwJ"},{"type":"text","value":"ierarchical ","position":{"start":{"line":3,"column":1},"end":{"line":3,"column":1}},"key":"pM1PNtv2ib"},{"type":"strong","position":{"start":{"line":3,"column":1},"end":{"line":3,"column":1}},"children":[{"type":"text","value":"E","position":{"start":{"line":3,"column":1},"end":{"line":3,"column":1}},"key":"ysZWoLPZRT"}],"key":"uzmENNrEgO"},{"type":"text","value":"qual ","position":{"start":{"line":3,"column":1},"end":{"line":3,"column":1}},"key":"tquT8GhI6s"},{"type":"strong","position":{"start":{"line":3,"column":1},"end":{"line":3,"column":1}},"children":[{"type":"text","value":"A","position":{"start":{"line":3,"column":1},"end":{"line":3,"column":1}},"key":"gfrghyy3ks"}],"key":"iTdddCzyIC"},{"type":"text","value":"rea iso","position":{"start":{"line":3,"column":1},"end":{"line":3,"column":1}},"key":"iPzkidKbIy"},{"type":"strong","position":{"start":{"line":3,"column":1},"end":{"line":3,"column":1}},"children":[{"type":"text","value":"L","position":{"start":{"line":3,"column":1},"end":{"line":3,"column":1}},"key":"n4vaivuwCv"}],"key":"oED9yRjDRr"},{"type":"text","value":"atitude ","position":{"start":{"line":3,"column":1},"end":{"line":3,"column":1}},"key":"npQ6aZlMPQ"},{"type":"strong","position":{"start":{"line":3,"column":1},"end":{"line":3,"column":1}},"children":[{"type":"text","value":"Pix","position":{"start":{"line":3,"column":1},"end":{"line":3,"column":1}},"key":"uSbI6Ra1qC"}],"key":"VrLQAdp0jA"},{"type":"text","value":"elation (HEALPix)","position":{"start":{"line":3,"column":1},"end":{"line":3,"column":1}},"key":"ZngWwBALdF"}],"urlSource":"https://healpix.sourceforge.io/","key":"U1Ji5GUbtQ"},{"type":"text","value":". However, rather than duplicating tons of information that is already available at HEALPix resources, we will try guiding the Pythia’s community in the right direction to access those resources.","position":{"start":{"line":3,"column":1},"end":{"line":3,"column":1}},"key":"ktIARycPms"}],"key":"glvmDYmqB2"},{"type":"heading","depth":3,"position":{"start":{"line":5,"column":1},"end":{"line":5,"column":1}},"children":[{"type":"text","value":"In this section, you’ll learn:","position":{"start":{"line":5,"column":1},"end":{"line":5,"column":1}},"key":"LHtaPmLzNV"}],"identifier":"in-this-section-youll-learn","label":"In this section, you’ll learn:","html_id":"in-this-section-youll-learn","implicit":true,"key":"F2NaMrQSlE"},{"type":"list","ordered":false,"spread":false,"position":{"start":{"line":7,"column":1},"end":{"line":10,"column":1}},"children":[{"type":"listItem","spread":true,"position":{"start":{"line":7,"column":1},"end":{"line":7,"column":1}},"children":[{"type":"paragraph","children":[{"type":"text","value":"What is HEALPix?","position":{"start":{"line":7,"column":1},"end":{"line":7,"column":1}},"key":"hitppmn6Ug"}],"key":"gErnksrTW2"}],"key":"tq0iT446Bf"},{"type":"listItem","spread":true,"position":{"start":{"line":8,"column":1},"end":{"line":8,"column":1}},"children":[{"type":"paragraph","children":[{"type":"text","value":"What resources can lead you to learn more about HEALPix?","position":{"start":{"line":8,"column":1},"end":{"line":8,"column":1}},"key":"DULDQJySs8"}],"key":"oUruXvyBaA"}],"key":"Zm7reP7FqX"},{"type":"listItem","spread":true,"position":{"start":{"line":9,"column":1},"end":{"line":10,"column":1}},"children":[{"type":"paragraph","children":[{"type":"text","value":"Why HEALPix?","position":{"start":{"line":9,"column":1},"end":{"line":9,"column":1}},"key":"CKRy9z4Ebs"}],"key":"EsruEcGQBs"}],"key":"zYrfMEWCWF"}],"key":"S92bLv0ZeJ"},{"type":"heading","depth":3,"position":{"start":{"line":11,"column":1},"end":{"line":11,"column":1}},"children":[{"type":"text","value":"Related Documentation","position":{"start":{"line":11,"column":1},"end":{"line":11,"column":1}},"key":"fxkQp2eU4U"}],"identifier":"related-documentation","label":"Related Documentation","html_id":"related-documentation","implicit":true,"key":"KUwZtzSZnU"},{"type":"list","ordered":false,"spread":false,"position":{"start":{"line":13,"column":1},"end":{"line":17,"column":1}},"children":[{"type":"listItem","spread":true,"position":{"start":{"line":13,"column":1},"end":{"line":13,"column":1}},"children":[{"type":"paragraph","children":[{"type":"link","url":"https://healpix.sourceforge.io/","position":{"start":{"line":13,"column":1},"end":{"line":13,"column":1}},"children":[{"type":"text","value":"HEALPix Homepage","position":{"start":{"line":13,"column":1},"end":{"line":13,"column":1}},"key":"byJpLzhMku"}],"urlSource":"https://healpix.sourceforge.io/","key":"wgKZMqrEXL"}],"key":"Y25N6gHdUm"}],"key":"ZyMGacKOXC"},{"type":"listItem","spread":true,"position":{"start":{"line":14,"column":1},"end":{"line":14,"column":1}},"children":[{"type":"paragraph","children":[{"type":"link","url":"https://healpix.sourceforge.io/documentation.php","position":{"start":{"line":14,"column":1},"end":{"line":14,"column":1}},"children":[{"type":"text","value":"HEALPix Documentation","position":{"start":{"line":14,"column":1},"end":{"line":14,"column":1}},"key":"Sqnqia77g2"}],"urlSource":"https://healpix.sourceforge.io/documentation.php","key":"O8Vmn9iWvj"}],"key":"mhouj9l1wv"}],"key":"EmqWjUPzd0"},{"type":"listItem","spread":true,"position":{"start":{"line":15,"column":1},"end":{"line":15,"column":1}},"children":[{"type":"paragraph","children":[{"type":"link","url":"https://healpix.sourceforge.io/resources.php","position":{"start":{"line":15,"column":1},"end":{"line":15,"column":1}},"children":[{"type":"text","value":"HEALPix Resources","position":{"start":{"line":15,"column":1},"end":{"line":15,"column":1}},"key":"XaR6FP3bBn"}],"urlSource":"https://healpix.sourceforge.io/resources.php","key":"i12IvXfygy"}],"key":"ZNnYv5rE1y"}],"key":"EIZD9mUQqU"},{"type":"listItem","spread":true,"position":{"start":{"line":16,"column":1},"end":{"line":17,"column":1}},"children":[{"type":"paragraph","children":[{"type":"link","url":"https://healpix.sourceforge.io/support.php","position":{"start":{"line":16,"column":1},"end":{"line":16,"column":1}},"children":[{"type":"text","value":"HEALPix Support","position":{"start":{"line":16,"column":1},"end":{"line":16,"column":1}},"key":"CtlPE9LHwB"}],"urlSource":"https://healpix.sourceforge.io/support.php","key":"RnacD3lF7k"}],"key":"cukp8nAo0R"}],"key":"RyLnf9afmw"}],"key":"xaClLfgHSN"},{"type":"heading","depth":3,"position":{"start":{"line":18,"column":1},"end":{"line":18,"column":1}},"children":[{"type":"text","value":"Prerequisites","position":{"start":{"line":18,"column":1},"end":{"line":18,"column":1}},"key":"HNTemtvYYq"}],"identifier":"prerequisites","label":"Prerequisites","html_id":"prerequisites","implicit":true,"key":"mZIjPeyola"},{"type":"table","position":{"start":{"line":20,"column":1},"end":{"line":22,"column":1}},"children":[{"type":"tableRow","position":{"start":{"line":20,"column":1},"end":{"line":20,"column":1}},"children":[{"type":"tableCell","header":true,"position":{"start":{"line":20,"column":1},"end":{"line":20,"column":1}},"children":[{"type":"text","value":"Concepts","position":{"start":{"line":20,"column":1},"end":{"line":20,"column":1}},"key":"NF6Uoubhpo"}],"key":"hkmkIxtJOs"},{"type":"tableCell","header":true,"position":{"start":{"line":20,"column":1},"end":{"line":20,"column":1}},"children":[{"type":"text","value":"Importance","position":{"start":{"line":20,"column":1},"end":{"line":20,"column":1}},"key":"njlQZwl7ed"}],"key":"Bi23ZFFfXk"},{"type":"tableCell","header":true,"position":{"start":{"line":20,"column":1},"end":{"line":20,"column":1}},"children":[{"type":"text","value":"Notes","position":{"start":{"line":20,"column":1},"end":{"line":20,"column":1}},"key":"Bni2H5xnH7"}],"key":"EGovUrT0V9"}],"key":"JaPx19T0em"},{"type":"tableRow","position":{"start":{"line":22,"column":1},"end":{"line":22,"column":1}},"children":[{"type":"tableCell","position":{"start":{"line":22,"column":1},"end":{"line":22,"column":1}},"children":[{"type":"cite","url":"https://doi.org/10.1002/9781118786352.wbieg1050","position":{"start":{"line":22,"column":1},"end":{"line":22,"column":1}},"children":[{"type":"text","value":"Discrete Global Grid Systems","position":{"start":{"line":22,"column":1},"end":{"line":22,"column":1}},"key":"xEInKwOFfB"}],"kind":"narrative","label":"Peterson_2017","identifier":"https://doi.org/10.1002/9781118786352.wbieg1050","enumerator":"1","key":"dIWLXOab6F"}],"key":"demAdfzQLz"},{"type":"tableCell","position":{"start":{"line":22,"column":1},"end":{"line":22,"column":1}},"children":[{"type":"text","value":"Helpful","position":{"start":{"line":22,"column":1},"end":{"line":22,"column":1}},"key":"hniT6Vd6F8"}],"key":"yusuXDF7FB"},{"type":"tableCell","position":{"start":{"line":22,"column":1},"end":{"line":22,"column":1}},"children":[],"key":"LgWYsKwFDO"}],"key":"soXHKCb011"}],"key":"tXeUdPJkYg"},{"type":"paragraph","position":{"start":{"line":24,"column":1},"end":{"line":24,"column":1}},"children":[{"type":"strong","position":{"start":{"line":24,"column":1},"end":{"line":24,"column":1}},"children":[{"type":"text","value":"Time to learn","position":{"start":{"line":24,"column":1},"end":{"line":24,"column":1}},"key":"m5cPtDvEBQ"}],"key":"HukCXzu36e"},{"type":"text","value":": 10 minutes","position":{"start":{"line":24,"column":1},"end":{"line":24,"column":1}},"key":"stH2wvCxsW"}],"key":"OxiEDYjeag"},{"type":"thematicBreak","position":{"start":{"line":26,"column":1},"end":{"line":26,"column":1}},"key":"zvJYM6hmcy"}],"key":"fN3AVQE6ns"},{"type":"block","kind":"notebook-content","children":[{"type":"heading","depth":2,"position":{"start":{"line":1,"column":1},"end":{"line":1,"column":1}},"children":[{"type":"text","value":"What is HEALPix?","position":{"start":{"line":1,"column":1},"end":{"line":1,"column":1}},"key":"UvopuiZHXH"}],"identifier":"what-is-healpix","label":"What is HEALPix?","html_id":"what-is-healpix","implicit":true,"key":"yQ9IBqvrOd"}],"key":"BP1T46pxoo"},{"type":"block","kind":"notebook-content","children":[{"type":"paragraph","position":{"start":{"line":1,"column":1},"end":{"line":1,"column":1}},"children":[{"type":"text","value":"HEALPix is a high resolution discretization framework to provide equal area, iso-Latitude pixelation of a sphere for fast analysis of data distributed on it, which produces a subdivision of the spherical surface in which each pixel covers the same surface area as every other pixel at a given resolution level.","position":{"start":{"line":1,"column":1},"end":{"line":1,"column":1}},"key":"dC4ebFrWra"}],"key":"t1lpBKEixq"},{"type":"paragraph","position":{"start":{"line":3,"column":1},"end":{"line":3,"column":1}},"children":[{"type":"text","value":"HEALPix was originally devised to support fast and accurate mathematical calculations on a spherical discretization at sufficiently high resolution levels for satellite missions to measure the cosmic microwave background (CMB), and it has later been adopted to geoscience applications as well.","position":{"start":{"line":3,"column":1},"end":{"line":3,"column":1}},"key":"KoVIWOPbyE"}],"key":"eOrXDddxzz"},{"type":"paragraph","position":{"start":{"line":5,"column":1},"end":{"line":5,"column":1}},"children":[{"type":"text","value":"Be sure to check out the ","position":{"start":{"line":5,"column":1},"end":{"line":5,"column":1}},"key":"aBgFZ0ZTGT"},{"type":"link","url":"https://healpix.sourceforge.io/index.php","position":{"start":{"line":5,"column":1},"end":{"line":5,"column":1}},"children":[{"type":"text","value":"HEALPix home page","position":{"start":{"line":5,"column":1},"end":{"line":5,"column":1}},"key":"QYPF1mtdC8"}],"urlSource":"https://healpix.sourceforge.io/index.php","key":"c2vN12NoOy"},{"type":"text","value":" and the References at the end of this section for further details.","position":{"start":{"line":5,"column":1},"end":{"line":5,"column":1}},"key":"VRvGFfPvnY"}],"key":"cMzjdWonL7"},{"type":"paragraph","position":{"start":{"line":7,"column":1},"end":{"line":10,"column":1}},"children":[{"type":"image","url":"/healpix-cookbook/build/905fe1ae8d9a0e41b8fe13928c963fdd.jpeg","alt":"Matplotlib Logo","width":250,"key":"h0gwIS6qjp","urlSource":"https://healpix.sourceforge.io/images/gorski_f1.jpg"}],"key":"l6e6D2FkA1"}],"key":"m7Gc9JEijz"},{"type":"block","kind":"notebook-content","children":[{"type":"heading","depth":2,"position":{"start":{"line":1,"column":1},"end":{"line":1,"column":1}},"children":[{"type":"text","value":"Why HEALPix?","position":{"start":{"line":1,"column":1},"end":{"line":1,"column":1}},"key":"s3Zxopx6aP"}],"identifier":"why-healpix","label":"Why HEALPix?","html_id":"why-healpix","implicit":true,"key":"J3KreGzyRU"}],"key":"KGdbDMgq8R"},{"type":"block","kind":"notebook-content","children":[{"type":"paragraph","position":{"start":{"line":1,"column":1},"end":{"line":1,"column":1}},"children":[{"type":"text","value":"Three key features of HEALPix are:","position":{"start":{"line":1,"column":1},"end":{"line":1,"column":1}},"key":"XNyYnlOFAJ"}],"key":"BB5AqPAVk5"},{"type":"list","ordered":false,"spread":false,"position":{"start":{"line":3,"column":1},"end":{"line":6,"column":1}},"children":[{"type":"listItem","spread":true,"position":{"start":{"line":3,"column":1},"end":{"line":3,"column":1}},"children":[{"type":"paragraph","children":[{"type":"text","value":"The sphere is hierarchically tessellated into curvilinear quadrilaterals","position":{"start":{"line":3,"column":1},"end":{"line":3,"column":1}},"key":"sIOakwHEMG"}],"key":"rMIlyWW8na"}],"key":"pqGhub4P1W"},{"type":"listItem","spread":true,"position":{"start":{"line":4,"column":1},"end":{"line":4,"column":1}},"children":[{"type":"paragraph","children":[{"type":"text","value":"Areas of all pixels at a given resolution are identical","position":{"start":{"line":4,"column":1},"end":{"line":4,"column":1}},"key":"Ut2Y3kcp8p"}],"key":"c87uGVGMCP"}],"key":"MXMG22cZlx"},{"type":"listItem","spread":true,"position":{"start":{"line":5,"column":1},"end":{"line":6,"column":1}},"children":[{"type":"paragraph","children":[{"type":"text","value":"Pixels are distributed on lines of constant latitude","position":{"start":{"line":5,"column":1},"end":{"line":5,"column":1}},"key":"KG6ZgVJ5zk"}],"key":"C7ogKOa8B3"}],"key":"P49MGgAaSg"}],"key":"YJrQARGQqi"},{"type":"paragraph","position":{"start":{"line":7,"column":1},"end":{"line":7,"column":1}},"children":[{"type":"text","value":"These properties make HEALPix a good gridding choice to facilitate fast and accurate statistical and spherical analysis for high-resolution data such as spherical harmonics.","position":{"start":{"line":7,"column":1},"end":{"line":7,"column":1}},"key":"vffOetFKp8"}],"key":"CpGzn52fIA"}],"key":"rNyyEXVoyf"},{"type":"block","kind":"notebook-content","children":[{"type":"heading","depth":2,"position":{"start":{"line":1,"column":1},"end":{"line":1,"column":1}},"children":[{"type":"text","value":"Where to learn more about HEALPix?","position":{"start":{"line":1,"column":1},"end":{"line":1,"column":1}},"key":"j7cpWUyqww"}],"identifier":"where-to-learn-more-about-healpix","label":"Where to learn more about HEALPix?","html_id":"where-to-learn-more-about-healpix","implicit":true,"key":"O84UFjDT3F"}],"key":"YKky38nWOw"},{"type":"block","kind":"notebook-content","children":[{"type":"paragraph","position":{"start":{"line":1,"column":1},"end":{"line":1,"column":1}},"children":[{"type":"text","value":"In addition to the ","position":{"start":{"line":1,"column":1},"end":{"line":1,"column":1}},"key":"PvYYDbDAiO"},{"type":"crossReference","position":{"start":{"line":1,"column":1},"end":{"line":1,"column":1}},"children":[{"type":"text","value":"Related Documentation","position":{"start":{"line":1,"column":1},"end":{"line":1,"column":1}},"key":"gnSv1uiZZn"}],"identifier":"related-documentation","label":"related-documentation","kind":"heading","template":"{name}","resolved":true,"html_id":"related-documentation","key":"jRdaA8tBWi"},{"type":"text","value":" provided in the beginning of this notebook, there are some good resources that you can further learn HEALPix through. In this part, we’d like to introduce one of them, easy.gems:","position":{"start":{"line":1,"column":1},"end":{"line":1,"column":1}},"key":"cStZPsieTP"}],"key":"k5TL0Ln5H0"}],"key":"pdFCcX8bpT"},{"type":"block","kind":"notebook-content","children":[{"type":"heading","depth":3,"position":{"start":{"line":1,"column":1},"end":{"line":1,"column":1}},"children":[{"type":"text","value":"easy.gems","position":{"start":{"line":1,"column":1},"end":{"line":1,"column":1}},"key":"OFZ4o9jbAA"}],"identifier":"easy-gems","label":"easy.gems","html_id":"easy-gems","implicit":true,"key":"kxO734sCwf"},{"type":"paragraph","position":{"start":{"line":3,"column":1},"end":{"line":3,"column":1}},"children":[{"type":"link","url":"https://www.dkrz.de/en","position":{"start":{"line":3,"column":1},"end":{"line":3,"column":1}},"children":[{"type":"text","value":"DKRZ (The German Climate Computing Center)","position":{"start":{"line":3,"column":1},"end":{"line":3,"column":1}},"key":"lJ8SBNkxcX"}],"urlSource":"https://www.dkrz.de/en","key":"mCTDuYHxyc"},{"type":"text","value":" created ","position":{"start":{"line":3,"column":1},"end":{"line":3,"column":1}},"key":"LLsvWYrHFq"},{"type":"link","url":"https://easy.gems.dkrz.de/index.html","position":{"start":{"line":3,"column":1},"end":{"line":3,"column":1}},"children":[{"type":"text","value":"easy.gems","position":{"start":{"line":3,"column":1},"end":{"line":3,"column":1}},"key":"gggc6wMxoE"}],"urlSource":"https://easy.gems.dkrz.de/index.html","key":"v9eIIKJYKy"},{"type":"text","value":" for documenting high-resolution climate simulation output and its analysis, which was started within the frame of the ","position":{"start":{"line":3,"column":1},"end":{"line":3,"column":1}},"key":"Ye5Xo8ahbf"},{"type":"link","url":"https://www.esiwace.eu/the-project/past-phases/dyamond-initiative","position":{"start":{"line":3,"column":1},"end":{"line":3,"column":1}},"children":[{"type":"text","value":"DYAMOND intercomparison initiative","position":{"start":{"line":3,"column":1},"end":{"line":3,"column":1}},"key":"Zq0DkJsLFQ"}],"urlSource":"https://www.esiwace.eu/the-project/past-phases/dyamond-initiative","key":"DJHJz7Tm1T"},{"type":"text","value":".","position":{"start":{"line":3,"column":1},"end":{"line":3,"column":1}},"key":"wrXZYOyaO4"}],"key":"mSBS8S3iEp"},{"type":"paragraph","position":{"start":{"line":5,"column":1},"end":{"line":5,"column":1}},"children":[{"type":"text","value":"Since output in multiple resolutions (hierarchical) is written on the HEALPix grid in order to simplify and speed up analysis, easy.gems provides ","position":{"start":{"line":5,"column":1},"end":{"line":5,"column":1}},"key":"jzuzZ610su"},{"type":"link","url":"https://easy.gems.dkrz.de/Processing/healpix/index.html#","position":{"start":{"line":5,"column":1},"end":{"line":5,"column":1}},"children":[{"type":"text","value":"documentation","position":{"start":{"line":5,"column":1},"end":{"line":5,"column":1}},"key":"Fv6XaEzKBp"}],"urlSource":"https://easy.gems.dkrz.de/Processing/healpix/index.html#","key":"TdSyMFI92P"},{"type":"text","value":" for a range of applications such as getting started with HEALPix, using HEALPix analysis and plotting functionality on the simulation data, and performing conversions between HEALPix and other grid types.","position":{"start":{"line":5,"column":1},"end":{"line":5,"column":1}},"key":"K0QARGPPlk"}],"key":"C2oOak69y0"},{"type":"paragraph","position":{"start":{"line":7,"column":1},"end":{"line":7,"column":1}},"children":[{"type":"text","value":"The ","position":{"start":{"line":7,"column":1},"end":{"line":7,"column":1}},"key":"HPj4SoAzYF"},{"type":"link","url":"/notebooks/easygems","position":{"start":{"line":7,"column":1},"end":{"line":7,"column":1}},"children":[{"type":"text","value":"next section","position":{"start":{"line":7,"column":1},"end":{"line":7,"column":1}},"key":"YnK67rHQ43"}],"urlSource":"01-easygems","dataUrl":"/notebooks.easygems.json","internal":true,"protocol":"file","key":"XSTdSU7Q9s"},{"type":"text","value":" will showcase an easy.gems workflow that loads in, manipulates, analyzes, and visualizes HEALpix data, which uses easy.gems functions and other scientific Python ecosystem packages’ functionality recommended by easy.gems.","position":{"start":{"line":7,"column":1},"end":{"line":7,"column":1}},"key":"e0zOZf5zOC"}],"key":"o1JmOK2DL6"}],"key":"mK2J5HXlpV"},{"type":"block","kind":"notebook-content","children":[{"type":"heading","depth":2,"position":{"start":{"line":1,"column":1},"end":{"line":1,"column":1}},"children":[{"type":"text","value":"References","position":{"start":{"line":1,"column":1},"end":{"line":1,"column":1}},"key":"IFxV1X0A0n"}],"identifier":"references","label":"References","html_id":"references","implicit":true,"key":"qBn2eJxsCg"},{"type":"paragraph","position":{"start":{"line":3,"column":1},"end":{"line":3,"column":1}},"children":[{"type":"cite","url":"https://iopscience.iop.org/article/10.1086/427976/meta","position":{"start":{"line":3,"column":1},"end":{"line":3,"column":1}},"children":[{"type":"text","value":"Gorski et al. 2005 “HEALPix: A framework for high-resolution discretization and fast analysis of data distributed on the sphere”","position":{"start":{"line":3,"column":1},"end":{"line":3,"column":1}},"key":"TC5QJ1HuBb"}],"kind":"narrative","label":"Gorski_2005","identifier":"https://iopscience.iop.org/article/10.1086/427976/meta","enumerator":"2","key":"knsTX4BeuI"}],"key":"LepWFatIgp"},{"type":"paragraph","position":{"start":{"line":5,"column":1},"end":{"line":5,"column":1}},"children":[{"type":"cite","url":"https://doi.org/10.1002/9781118786352.wbieg1050","position":{"start":{"line":5,"column":1},"end":{"line":5,"column":1}},"children":[{"type":"text","value":"Peterson et al. 2016 “Discrete global grid systems”","position":{"start":{"line":5,"column":1},"end":{"line":5,"column":1}},"key":"GIuMOHszcQ"}],"kind":"narrative","label":"Peterson_2017","identifier":"https://doi.org/10.1002/9781118786352.wbieg1050","enumerator":"1","key":"EzwRjfZ0EO"}],"key":"UPe1ET0HAH"}],"key":"jtN8KuHrIc"},{"type":"block","kind":"notebook-content","children":[{"type":"heading","depth":2,"position":{"start":{"line":1,"column":1},"end":{"line":1,"column":1}},"children":[{"type":"text","value":"What is next?","position":{"start":{"line":1,"column":1},"end":{"line":1,"column":1}},"key":"oZdBcTnlPC"}],"identifier":"what-is-next","label":"What is next?","html_id":"what-is-next","implicit":true,"key":"jEFkynFJAR"},{"type":"paragraph","position":{"start":{"line":3,"column":1},"end":{"line":3,"column":1}},"children":[{"type":"text","value":"The ","position":{"start":{"line":3,"column":1},"end":{"line":3,"column":1}},"key":"yHqb37abrL"},{"type":"link","url":"/notebooks/easygems","position":{"start":{"line":3,"column":1},"end":{"line":3,"column":1}},"children":[{"type":"text","value":"next section","position":{"start":{"line":3,"column":1},"end":{"line":3,"column":1}},"key":"NxuJiGuomn"}],"urlSource":"01-easygems","dataUrl":"/notebooks.easygems.json","internal":true,"protocol":"file","key":"oOMxjIKBhG"},{"type":"text","value":" will provide an easy.gems workflow that uses HEALPix data.","position":{"start":{"line":3,"column":1},"end":{"line":3,"column":1}},"key":"s6cKRWq2br"}],"key":"buvTOyE0zP"}],"key":"gxhxCFhtut"}],"key":"lc8YsBWCEU"},"references":{"cite":{"order":["Peterson_2017","Gorski_2005"],"data":{"Peterson_2017":{"label":"Peterson_2017","enumerator":"1","doi":"10.1002/9781118786352.wbieg1050","html":"Peterson, P. R. (2017). Discrete Global Grid Systems. In <i>International Encyclopedia of Geography</i> (pp. 1–10). Wiley. <a target=\"_blank\" rel=\"noreferrer\" href=\"https://doi.org/10.1002/9781118786352.wbieg1050\">10.1002/9781118786352.wbieg1050</a>","url":"https://doi.org/10.1002/9781118786352.wbieg1050"},"Gorski_2005":{"label":"Gorski_2005","enumerator":"2","doi":"10.1086/427976","html":"Gorski, K. M., Hivon, E., Banday, A. J., Wandelt, B. D., Hansen, F. K., Reinecke, M., & Bartelmann, M. (2005). HEALPix: A Framework for High‐Resolution Discretization and Fast Analysis of Data Distributed on the Sphere. <i>The Astrophysical Journal</i>, <i>622</i>(2), 759–771. <a target=\"_blank\" rel=\"noreferrer\" href=\"https://doi.org/10.1086/427976\">10.1086/427976</a>","url":"https://doi.org/10.1086/427976"}}}},"footer":{"navigation":{"prev":{"title":"How to Cite This Cookbook","url":"/notebooks/how-to-cite","group":"Preamble"},"next":{"title":"easy.gems for HEALPix Analysis & Visualization","url":"/notebooks/easygems","group":"HEALPix Analysis & Visualization"}}},"domain":"http://localhost:3000"}