{"version":3,"kind":"Notebook","sha256":"26b8067b96f2418bf8db2e802a7820773ed89f3eb404d41d1c6058b0f66ae36d","slug":"notebooks.healpix","location":"/notebooks/00-healpix.ipynb","dependencies":[],"frontmatter":{"title":"HEALPix Overview","content_includes_title":false,"kernelspec":{"name":"python3","display_name":"Python 3 (ipykernel)","language":"python"},"authors":[{"nameParsed":{"literal":"Project Pythia Community","given":"Project Pythia","family":"Community"},"name":"Project Pythia Community","url":"https://projectpythia.org/","id":"contributors-myst-generated-uid-0"}],"open_access":true,"license":{"content":{"id":"CC-BY-4.0","url":"https://creativecommons.org/licenses/by/4.0/","name":"Creative Commons Attribution 4.0 International","free":true,"CC":true},"code":{"id":"Apache-2.0","url":"https://opensource.org/licenses/Apache-2.0","name":"Apache License 2.0","free":true,"osi":true}},"github":"https://github.com/projectpythia/healpix-cookbook","copyright":"2025","affiliations":[{"id":"UAlbany","name":"University at Albany (SUNY)","department":"Atmospheric and Environmental Sciences","url":"https://www.albany.edu/daes"},{"id":"CISL","name":"NSF National Center for Atmospheric Research","department":"Computational and Information Systems Lab","url":"https://www.cisl.ucar.edu"},{"id":"Unidata","name":"NSF Unidata","url":"https://www.unidata.ucar.edu"},{"id":"Argonne","name":"Argonne National Laboratory","department":"Environmental Science Division","url":"https://www.anl.gov/evs"},{"id":"CarbonPlan","name":"CarbonPlan","url":"https://carbonplan.org"},{"id":"NVIDIA","name":"NVIDIA Corporation","url":"https://www.nvidia.com/"}],"numbering":{"title":{"offset":1}},"source_url":"https://github.com/projectpythia/healpix-cookbook/blob/main/notebooks/00-healpix.ipynb","edit_url":"https://github.com/projectpythia/healpix-cookbook/edit/main/notebooks/00-healpix.ipynb","thumbnail":"/healpix-cookbook/build/905fe1ae8d9a0e41b8fe13928c963fdd.jpeg","exports":[{"format":"ipynb","filename":"00-healpix.ipynb","url":"/healpix-cookbook/build/00-healpix-7937e1c52375181a8bdc6ab3e6efa824.ipynb"}]},"widgets":{},"mdast":{"type":"root","children":[{"type":"block","kind":"notebook-content","children":[{"type":"paragraph","position":{"start":{"line":3,"column":1},"end":{"line":3,"column":1}},"children":[{"type":"text","value":"This first section of the cookbook aims at providing the reader with an introduction to ","position":{"start":{"line":3,"column":1},"end":{"line":3,"column":1}},"key":"Elt0DEyhlm"},{"type":"link","url":"https://healpix.sourceforge.io/","position":{"start":{"line":3,"column":1},"end":{"line":3,"column":1}},"children":[{"type":"strong","position":{"start":{"line":3,"column":1},"end":{"line":3,"column":1}},"children":[{"type":"text","value":"H","position":{"start":{"line":3,"column":1},"end":{"line":3,"column":1}},"key":"aHxlpmmMlU"}],"key":"l2wi1vtdRE"},{"type":"text","value":"ierarchical ","position":{"start":{"line":3,"column":1},"end":{"line":3,"column":1}},"key":"ZAD50xQGo8"},{"type":"strong","position":{"start":{"line":3,"column":1},"end":{"line":3,"column":1}},"children":[{"type":"text","value":"E","position":{"start":{"line":3,"column":1},"end":{"line":3,"column":1}},"key":"Hi94FNl8ne"}],"key":"Vy8F9n5NB8"},{"type":"text","value":"qual ","position":{"start":{"line":3,"column":1},"end":{"line":3,"column":1}},"key":"mvGOS2shQF"},{"type":"strong","position":{"start":{"line":3,"column":1},"end":{"line":3,"column":1}},"children":[{"type":"text","value":"A","position":{"start":{"line":3,"column":1},"end":{"line":3,"column":1}},"key":"asBG7eslYD"}],"key":"Xq7LZkwBSj"},{"type":"text","value":"rea iso","position":{"start":{"line":3,"column":1},"end":{"line":3,"column":1}},"key":"FXdPd8wZx3"},{"type":"strong","position":{"start":{"line":3,"column":1},"end":{"line":3,"column":1}},"children":[{"type":"text","value":"L","position":{"start":{"line":3,"column":1},"end":{"line":3,"column":1}},"key":"qvyrwplnOz"}],"key":"sJoO4hMGWY"},{"type":"text","value":"atitude ","position":{"start":{"line":3,"column":1},"end":{"line":3,"column":1}},"key":"uuFygrpqDX"},{"type":"strong","position":{"start":{"line":3,"column":1},"end":{"line":3,"column":1}},"children":[{"type":"text","value":"Pix","position":{"start":{"line":3,"column":1},"end":{"line":3,"column":1}},"key":"YicLS4zk6e"}],"key":"sxqjBQyRWR"},{"type":"text","value":"elation (HEALPix)","position":{"start":{"line":3,"column":1},"end":{"line":3,"column":1}},"key":"JUhIZgMdPv"}],"urlSource":"https://healpix.sourceforge.io/","key":"QXMxXev40l"},{"type":"text","value":". However, rather than duplicating tons of information that is already available at HEALPix resources, we will try guiding the Pythia’s community in the right direction to access those resources.","position":{"start":{"line":3,"column":1},"end":{"line":3,"column":1}},"key":"N4YAhMpn5i"}],"key":"EAKK3XBACw"},{"type":"heading","depth":3,"position":{"start":{"line":5,"column":1},"end":{"line":5,"column":1}},"children":[{"type":"text","value":"In this section, you’ll learn:","position":{"start":{"line":5,"column":1},"end":{"line":5,"column":1}},"key":"jnoaucUxDe"}],"identifier":"in-this-section-youll-learn","label":"In this section, you’ll learn:","html_id":"in-this-section-youll-learn","implicit":true,"key":"FCzg3sbdt9"},{"type":"list","ordered":false,"spread":false,"position":{"start":{"line":7,"column":1},"end":{"line":10,"column":1}},"children":[{"type":"listItem","spread":true,"position":{"start":{"line":7,"column":1},"end":{"line":7,"column":1}},"children":[{"type":"paragraph","children":[{"type":"text","value":"What is HEALPix?","position":{"start":{"line":7,"column":1},"end":{"line":7,"column":1}},"key":"My0Qv6nltX"}],"key":"BSk6ktZnqD"}],"key":"lzCUolB9Df"},{"type":"listItem","spread":true,"position":{"start":{"line":8,"column":1},"end":{"line":8,"column":1}},"children":[{"type":"paragraph","children":[{"type":"text","value":"What resources can lead you to learn more about HEALPix?","position":{"start":{"line":8,"column":1},"end":{"line":8,"column":1}},"key":"PW3Im1BhcD"}],"key":"kNZrZMo3sz"}],"key":"O3bFU9SFwz"},{"type":"listItem","spread":true,"position":{"start":{"line":9,"column":1},"end":{"line":10,"column":1}},"children":[{"type":"paragraph","children":[{"type":"text","value":"Why HEALPix?","position":{"start":{"line":9,"column":1},"end":{"line":9,"column":1}},"key":"ckrC7sIiwE"}],"key":"TD1ZDfqrJ5"}],"key":"QQ26BIYIV2"}],"key":"JKsmGeNce7"},{"type":"heading","depth":3,"position":{"start":{"line":11,"column":1},"end":{"line":11,"column":1}},"children":[{"type":"text","value":"Related Documentation","position":{"start":{"line":11,"column":1},"end":{"line":11,"column":1}},"key":"meOEuGBgZd"}],"identifier":"related-documentation","label":"Related Documentation","html_id":"related-documentation","implicit":true,"key":"bMcR30ItZn"},{"type":"list","ordered":false,"spread":false,"position":{"start":{"line":13,"column":1},"end":{"line":17,"column":1}},"children":[{"type":"listItem","spread":true,"position":{"start":{"line":13,"column":1},"end":{"line":13,"column":1}},"children":[{"type":"paragraph","children":[{"type":"link","url":"https://healpix.sourceforge.io/","position":{"start":{"line":13,"column":1},"end":{"line":13,"column":1}},"children":[{"type":"text","value":"HEALPix Homepage","position":{"start":{"line":13,"column":1},"end":{"line":13,"column":1}},"key":"zgBASC74eH"}],"urlSource":"https://healpix.sourceforge.io/","key":"vxy5W57YRA"}],"key":"FpbpTApPxn"}],"key":"AAC2ilhrbe"},{"type":"listItem","spread":true,"position":{"start":{"line":14,"column":1},"end":{"line":14,"column":1}},"children":[{"type":"paragraph","children":[{"type":"link","url":"https://healpix.sourceforge.io/documentation.php","position":{"start":{"line":14,"column":1},"end":{"line":14,"column":1}},"children":[{"type":"text","value":"HEALPix Documentation","position":{"start":{"line":14,"column":1},"end":{"line":14,"column":1}},"key":"ZrMshScaeu"}],"urlSource":"https://healpix.sourceforge.io/documentation.php","key":"wYzG1H6wZV"}],"key":"mjuyPN0Z7P"}],"key":"xUChzUX9YF"},{"type":"listItem","spread":true,"position":{"start":{"line":15,"column":1},"end":{"line":15,"column":1}},"children":[{"type":"paragraph","children":[{"type":"link","url":"https://healpix.sourceforge.io/resources.php","position":{"start":{"line":15,"column":1},"end":{"line":15,"column":1}},"children":[{"type":"text","value":"HEALPix Resources","position":{"start":{"line":15,"column":1},"end":{"line":15,"column":1}},"key":"VkqFW95xya"}],"urlSource":"https://healpix.sourceforge.io/resources.php","key":"vQHKHVGTrr"}],"key":"KihsnaTUAu"}],"key":"BVfM9Vd9mK"},{"type":"listItem","spread":true,"position":{"start":{"line":16,"column":1},"end":{"line":17,"column":1}},"children":[{"type":"paragraph","children":[{"type":"link","url":"https://healpix.sourceforge.io/support.php","position":{"start":{"line":16,"column":1},"end":{"line":16,"column":1}},"children":[{"type":"text","value":"HEALPix Support","position":{"start":{"line":16,"column":1},"end":{"line":16,"column":1}},"key":"YDh5IQvdXk"}],"urlSource":"https://healpix.sourceforge.io/support.php","key":"HdyEFG4bvk"}],"key":"MyA6ozPbGA"}],"key":"gG83VeTUZr"}],"key":"B7kbYqh2fh"},{"type":"heading","depth":3,"position":{"start":{"line":18,"column":1},"end":{"line":18,"column":1}},"children":[{"type":"text","value":"Prerequisites","position":{"start":{"line":18,"column":1},"end":{"line":18,"column":1}},"key":"Ibmn4mR5rg"}],"identifier":"prerequisites","label":"Prerequisites","html_id":"prerequisites","implicit":true,"key":"omYajbkIVo"},{"type":"table","position":{"start":{"line":20,"column":1},"end":{"line":22,"column":1}},"children":[{"type":"tableRow","position":{"start":{"line":20,"column":1},"end":{"line":20,"column":1}},"children":[{"type":"tableCell","header":true,"position":{"start":{"line":20,"column":1},"end":{"line":20,"column":1}},"children":[{"type":"text","value":"Concepts","position":{"start":{"line":20,"column":1},"end":{"line":20,"column":1}},"key":"X4IoVoHFNQ"}],"key":"jYZDPmFBAw"},{"type":"tableCell","header":true,"position":{"start":{"line":20,"column":1},"end":{"line":20,"column":1}},"children":[{"type":"text","value":"Importance","position":{"start":{"line":20,"column":1},"end":{"line":20,"column":1}},"key":"jJE8keZaV6"}],"key":"MLN8xqCb0y"},{"type":"tableCell","header":true,"position":{"start":{"line":20,"column":1},"end":{"line":20,"column":1}},"children":[{"type":"text","value":"Notes","position":{"start":{"line":20,"column":1},"end":{"line":20,"column":1}},"key":"Y9ahYYSj62"}],"key":"Tt40PiC8ig"}],"key":"C3vQfqnbUm"},{"type":"tableRow","position":{"start":{"line":22,"column":1},"end":{"line":22,"column":1}},"children":[{"type":"tableCell","position":{"start":{"line":22,"column":1},"end":{"line":22,"column":1}},"children":[{"type":"cite","url":"https://doi.org/10.1002/9781118786352.wbieg1050","position":{"start":{"line":22,"column":1},"end":{"line":22,"column":1}},"children":[{"type":"text","value":"Discrete Global Grid Systems","position":{"start":{"line":22,"column":1},"end":{"line":22,"column":1}},"key":"RK544Km0UV"}],"kind":"narrative","label":"Peterson_2017","identifier":"https://doi.org/10.1002/9781118786352.wbieg1050","enumerator":"1","key":"SKzciVktow"}],"key":"zosPLruDjb"},{"type":"tableCell","position":{"start":{"line":22,"column":1},"end":{"line":22,"column":1}},"children":[{"type":"text","value":"Helpful","position":{"start":{"line":22,"column":1},"end":{"line":22,"column":1}},"key":"odRIlMQhdh"}],"key":"mkuC4MtgHI"},{"type":"tableCell","position":{"start":{"line":22,"column":1},"end":{"line":22,"column":1}},"children":[],"key":"kID0hYrpkk"}],"key":"DfdATviSeO"}],"key":"s0KuAYOjf2"},{"type":"paragraph","position":{"start":{"line":24,"column":1},"end":{"line":24,"column":1}},"children":[{"type":"strong","position":{"start":{"line":24,"column":1},"end":{"line":24,"column":1}},"children":[{"type":"text","value":"Time to learn","position":{"start":{"line":24,"column":1},"end":{"line":24,"column":1}},"key":"ZRVPwcCudZ"}],"key":"ETbc86v9PP"},{"type":"text","value":": 10 minutes","position":{"start":{"line":24,"column":1},"end":{"line":24,"column":1}},"key":"v87WfK1EHe"}],"key":"NZFMxlKV8c"},{"type":"thematicBreak","position":{"start":{"line":26,"column":1},"end":{"line":26,"column":1}},"key":"ZApwR4l2XI"}],"key":"r0YFlBIQIc"},{"type":"block","kind":"notebook-content","children":[{"type":"heading","depth":2,"position":{"start":{"line":1,"column":1},"end":{"line":1,"column":1}},"children":[{"type":"text","value":"What is HEALPix?","position":{"start":{"line":1,"column":1},"end":{"line":1,"column":1}},"key":"hRmV0zBvi7"}],"identifier":"what-is-healpix","label":"What is HEALPix?","html_id":"what-is-healpix","implicit":true,"key":"HA0wdblwly"}],"key":"sZI1cYFRYF"},{"type":"block","kind":"notebook-content","children":[{"type":"paragraph","position":{"start":{"line":1,"column":1},"end":{"line":1,"column":1}},"children":[{"type":"text","value":"HEALPix is a high resolution discretization framework to provide equal area, iso-Latitude pixelation of a sphere for fast analysis of data distributed on it, which produces a subdivision of the spherical surface in which each pixel covers the same surface area as every other pixel at a given resolution level.","position":{"start":{"line":1,"column":1},"end":{"line":1,"column":1}},"key":"waHUlHo5td"}],"key":"txE3TezNmy"},{"type":"paragraph","position":{"start":{"line":3,"column":1},"end":{"line":3,"column":1}},"children":[{"type":"text","value":"HEALPix was originally devised to support fast and accurate mathematical calculations on a spherical discretization at sufficiently high resolution levels for satellite missions to measure the cosmic microwave background (CMB), and it has later been adopted to geoscience applications as well.","position":{"start":{"line":3,"column":1},"end":{"line":3,"column":1}},"key":"AXhjPn3unt"}],"key":"g4GB9IdMkn"},{"type":"paragraph","position":{"start":{"line":5,"column":1},"end":{"line":5,"column":1}},"children":[{"type":"text","value":"Be sure to check out the ","position":{"start":{"line":5,"column":1},"end":{"line":5,"column":1}},"key":"X9tsjB5tdL"},{"type":"link","url":"https://healpix.sourceforge.io/index.php","position":{"start":{"line":5,"column":1},"end":{"line":5,"column":1}},"children":[{"type":"text","value":"HEALPix home page","position":{"start":{"line":5,"column":1},"end":{"line":5,"column":1}},"key":"qmN8cfOjXC"}],"urlSource":"https://healpix.sourceforge.io/index.php","key":"kaiPQwvBfa"},{"type":"text","value":" and the References at the end of this section for further details.","position":{"start":{"line":5,"column":1},"end":{"line":5,"column":1}},"key":"JsY4gyB69s"}],"key":"QB2eMB0G0h"},{"type":"paragraph","position":{"start":{"line":7,"column":1},"end":{"line":10,"column":1}},"children":[{"type":"image","url":"/healpix-cookbook/build/905fe1ae8d9a0e41b8fe13928c963fdd.jpeg","alt":"Matplotlib Logo","width":250,"key":"wKip172gaC","urlSource":"https://healpix.sourceforge.io/images/gorski_f1.jpg"}],"key":"rOUeqmgJ7l"}],"key":"MtOnEjKbgm"},{"type":"block","kind":"notebook-content","children":[{"type":"heading","depth":2,"position":{"start":{"line":1,"column":1},"end":{"line":1,"column":1}},"children":[{"type":"text","value":"Why HEALPix?","position":{"start":{"line":1,"column":1},"end":{"line":1,"column":1}},"key":"e9XhPnkvER"}],"identifier":"why-healpix","label":"Why HEALPix?","html_id":"why-healpix","implicit":true,"key":"T275I6bEWc"}],"key":"kr4C7F95LN"},{"type":"block","kind":"notebook-content","children":[{"type":"paragraph","position":{"start":{"line":1,"column":1},"end":{"line":1,"column":1}},"children":[{"type":"text","value":"Three key features of HEALPix are:","position":{"start":{"line":1,"column":1},"end":{"line":1,"column":1}},"key":"CMi8JcQMgj"}],"key":"YSaVHOgzzh"},{"type":"list","ordered":false,"spread":false,"position":{"start":{"line":3,"column":1},"end":{"line":6,"column":1}},"children":[{"type":"listItem","spread":true,"position":{"start":{"line":3,"column":1},"end":{"line":3,"column":1}},"children":[{"type":"paragraph","children":[{"type":"text","value":"The sphere is hierarchically tessellated into curvilinear quadrilaterals","position":{"start":{"line":3,"column":1},"end":{"line":3,"column":1}},"key":"PocQwKNkbI"}],"key":"maBpvulsJG"}],"key":"npb1AzM7Co"},{"type":"listItem","spread":true,"position":{"start":{"line":4,"column":1},"end":{"line":4,"column":1}},"children":[{"type":"paragraph","children":[{"type":"text","value":"Areas of all pixels at a given resolution are identical","position":{"start":{"line":4,"column":1},"end":{"line":4,"column":1}},"key":"pn5QQFkbBL"}],"key":"aFL1qHaoky"}],"key":"FvM2biSH1j"},{"type":"listItem","spread":true,"position":{"start":{"line":5,"column":1},"end":{"line":6,"column":1}},"children":[{"type":"paragraph","children":[{"type":"text","value":"Pixels are distributed on lines of constant latitude","position":{"start":{"line":5,"column":1},"end":{"line":5,"column":1}},"key":"taQ3ewi4Dw"}],"key":"MYMLjOKm2N"}],"key":"QzPb0yQyW7"}],"key":"zOHortcUoJ"},{"type":"paragraph","position":{"start":{"line":7,"column":1},"end":{"line":7,"column":1}},"children":[{"type":"text","value":"These properties make HEALPix a good gridding choice to facilitate fast and accurate statistical and spherical analysis for high-resolution data such as spherical harmonics.","position":{"start":{"line":7,"column":1},"end":{"line":7,"column":1}},"key":"EVREiOXdG7"}],"key":"BaN0plI72s"}],"key":"wyOsKSXUgA"},{"type":"block","kind":"notebook-content","children":[{"type":"heading","depth":2,"position":{"start":{"line":1,"column":1},"end":{"line":1,"column":1}},"children":[{"type":"text","value":"Where to learn more about HEALPix?","position":{"start":{"line":1,"column":1},"end":{"line":1,"column":1}},"key":"F8tSeKfcmO"}],"identifier":"where-to-learn-more-about-healpix","label":"Where to learn more about HEALPix?","html_id":"where-to-learn-more-about-healpix","implicit":true,"key":"Hqor408sgj"}],"key":"ygVsqWIFet"},{"type":"block","kind":"notebook-content","children":[{"type":"paragraph","position":{"start":{"line":1,"column":1},"end":{"line":1,"column":1}},"children":[{"type":"text","value":"In addition to the ","position":{"start":{"line":1,"column":1},"end":{"line":1,"column":1}},"key":"ISeB1zb7ym"},{"type":"crossReference","position":{"start":{"line":1,"column":1},"end":{"line":1,"column":1}},"children":[{"type":"text","value":"Related Documentation","position":{"start":{"line":1,"column":1},"end":{"line":1,"column":1}},"key":"qiAihEkC7k"}],"identifier":"related-documentation","label":"related-documentation","kind":"heading","template":"{name}","resolved":true,"html_id":"related-documentation","key":"kTLrtUnzyN"},{"type":"text","value":" provided in the beginning of this notebook, there are some good resources that you can further learn HEALPix through. In this part, we’d like to introduce one of them, easy.gems:","position":{"start":{"line":1,"column":1},"end":{"line":1,"column":1}},"key":"XRUA1rRFoR"}],"key":"G5FOYpe7HW"}],"key":"sN2srvwKGj"},{"type":"block","kind":"notebook-content","children":[{"type":"heading","depth":3,"position":{"start":{"line":1,"column":1},"end":{"line":1,"column":1}},"children":[{"type":"text","value":"easy.gems","position":{"start":{"line":1,"column":1},"end":{"line":1,"column":1}},"key":"phkxzPICXj"}],"identifier":"easy-gems","label":"easy.gems","html_id":"easy-gems","implicit":true,"key":"lBfp77VnNz"},{"type":"paragraph","position":{"start":{"line":3,"column":1},"end":{"line":3,"column":1}},"children":[{"type":"link","url":"https://www.dkrz.de/en","position":{"start":{"line":3,"column":1},"end":{"line":3,"column":1}},"children":[{"type":"text","value":"DKRZ (The German Climate Computing Center)","position":{"start":{"line":3,"column":1},"end":{"line":3,"column":1}},"key":"PkP5BuZk1K"}],"urlSource":"https://www.dkrz.de/en","key":"IrwsHKaNhe"},{"type":"text","value":" created ","position":{"start":{"line":3,"column":1},"end":{"line":3,"column":1}},"key":"foK03w2qqn"},{"type":"link","url":"https://easy.gems.dkrz.de/index.html","position":{"start":{"line":3,"column":1},"end":{"line":3,"column":1}},"children":[{"type":"text","value":"easy.gems","position":{"start":{"line":3,"column":1},"end":{"line":3,"column":1}},"key":"MRtAmLhMLu"}],"urlSource":"https://easy.gems.dkrz.de/index.html","key":"plf5igPwJG"},{"type":"text","value":" for documenting high-resolution climate simulation output and its analysis, which was started within the frame of the ","position":{"start":{"line":3,"column":1},"end":{"line":3,"column":1}},"key":"PgQHo54G5Z"},{"type":"link","url":"https://www.esiwace.eu/the-project/past-phases/dyamond-initiative","position":{"start":{"line":3,"column":1},"end":{"line":3,"column":1}},"children":[{"type":"text","value":"DYAMOND intercomparison initiative","position":{"start":{"line":3,"column":1},"end":{"line":3,"column":1}},"key":"Iom1A1dWoc"}],"urlSource":"https://www.esiwace.eu/the-project/past-phases/dyamond-initiative","key":"AOJTXKrUWy"},{"type":"text","value":".","position":{"start":{"line":3,"column":1},"end":{"line":3,"column":1}},"key":"C72kcaRJ5S"}],"key":"M7YUJz14rN"},{"type":"paragraph","position":{"start":{"line":5,"column":1},"end":{"line":5,"column":1}},"children":[{"type":"text","value":"Since output in multiple resolutions (hierarchical) is written on the HEALPix grid in order to simplify and speed up analysis, easy.gems provides ","position":{"start":{"line":5,"column":1},"end":{"line":5,"column":1}},"key":"zDYsIXFWSz"},{"type":"link","url":"https://easy.gems.dkrz.de/Processing/healpix/index.html#","position":{"start":{"line":5,"column":1},"end":{"line":5,"column":1}},"children":[{"type":"text","value":"documentation","position":{"start":{"line":5,"column":1},"end":{"line":5,"column":1}},"key":"VWxXemdA4a"}],"urlSource":"https://easy.gems.dkrz.de/Processing/healpix/index.html#","key":"QfkreHP9cB"},{"type":"text","value":" for a range of applications such as getting started with HEALPix, using HEALPix analysis and plotting functionality on the simulation data, and performing conversions between HEALPix and other grid types.","position":{"start":{"line":5,"column":1},"end":{"line":5,"column":1}},"key":"R8T2evKKM1"}],"key":"b9j2Xt0neJ"},{"type":"paragraph","position":{"start":{"line":7,"column":1},"end":{"line":7,"column":1}},"children":[{"type":"text","value":"The ","position":{"start":{"line":7,"column":1},"end":{"line":7,"column":1}},"key":"mecxzNq3bz"},{"type":"link","url":"/notebooks/easygems","position":{"start":{"line":7,"column":1},"end":{"line":7,"column":1}},"children":[{"type":"text","value":"next section","position":{"start":{"line":7,"column":1},"end":{"line":7,"column":1}},"key":"bpQ2jknLSR"}],"urlSource":"01-easygems","dataUrl":"/notebooks.easygems.json","internal":true,"protocol":"file","key":"lFZeReD8Jc"},{"type":"text","value":" will showcase an easy.gems workflow that loads in, manipulates, analyzes, and visualizes HEALpix data, which uses easy.gems functions and other scientific Python ecosystem packages’ functionality recommended by easy.gems.","position":{"start":{"line":7,"column":1},"end":{"line":7,"column":1}},"key":"mUC6Drwg2D"}],"key":"zw2kXsQFPs"}],"key":"CcMIGeUO90"},{"type":"block","kind":"notebook-content","children":[{"type":"heading","depth":2,"position":{"start":{"line":1,"column":1},"end":{"line":1,"column":1}},"children":[{"type":"text","value":"References","position":{"start":{"line":1,"column":1},"end":{"line":1,"column":1}},"key":"zEtEX1O9FR"}],"identifier":"references","label":"References","html_id":"references","implicit":true,"key":"FVleXSya3P"},{"type":"paragraph","position":{"start":{"line":3,"column":1},"end":{"line":3,"column":1}},"children":[{"type":"cite","url":"https://iopscience.iop.org/article/10.1086/427976/meta","position":{"start":{"line":3,"column":1},"end":{"line":3,"column":1}},"children":[{"type":"text","value":"Gorski et al. 2005 “HEALPix: A framework for high-resolution discretization and fast analysis of data distributed on the sphere”","position":{"start":{"line":3,"column":1},"end":{"line":3,"column":1}},"key":"M3W3acaGyb"}],"kind":"narrative","label":"Gorski_2005","identifier":"https://iopscience.iop.org/article/10.1086/427976/meta","enumerator":"2","key":"MrUMP4qUwl"}],"key":"TYfY2L6XvP"},{"type":"paragraph","position":{"start":{"line":5,"column":1},"end":{"line":5,"column":1}},"children":[{"type":"cite","url":"https://doi.org/10.1002/9781118786352.wbieg1050","position":{"start":{"line":5,"column":1},"end":{"line":5,"column":1}},"children":[{"type":"text","value":"Peterson et al. 2016 “Discrete global grid systems”","position":{"start":{"line":5,"column":1},"end":{"line":5,"column":1}},"key":"CdIlgjPND0"}],"kind":"narrative","label":"Peterson_2017","identifier":"https://doi.org/10.1002/9781118786352.wbieg1050","enumerator":"1","key":"T0op0mBFQ2"}],"key":"thgzx0IMJH"}],"key":"sf5jSb8BEq"},{"type":"block","kind":"notebook-content","children":[{"type":"heading","depth":2,"position":{"start":{"line":1,"column":1},"end":{"line":1,"column":1}},"children":[{"type":"text","value":"What is next?","position":{"start":{"line":1,"column":1},"end":{"line":1,"column":1}},"key":"qxACdrQdXe"}],"identifier":"what-is-next","label":"What is next?","html_id":"what-is-next","implicit":true,"key":"MMC4as9A8X"},{"type":"paragraph","position":{"start":{"line":3,"column":1},"end":{"line":3,"column":1}},"children":[{"type":"text","value":"The ","position":{"start":{"line":3,"column":1},"end":{"line":3,"column":1}},"key":"qfNPM62vEC"},{"type":"link","url":"/notebooks/easygems","position":{"start":{"line":3,"column":1},"end":{"line":3,"column":1}},"children":[{"type":"text","value":"next section","position":{"start":{"line":3,"column":1},"end":{"line":3,"column":1}},"key":"Fm2BnBXH4G"}],"urlSource":"01-easygems","dataUrl":"/notebooks.easygems.json","internal":true,"protocol":"file","key":"UKzb9ilGl4"},{"type":"text","value":" will provide an easy.gems workflow that uses HEALPix data.","position":{"start":{"line":3,"column":1},"end":{"line":3,"column":1}},"key":"oLrDuXQf8b"}],"key":"pWR4brK5B7"}],"key":"TJvmjkOa1O"}],"key":"N8p0lPWkUY"},"references":{"cite":{"order":["Peterson_2017","Gorski_2005"],"data":{"Peterson_2017":{"label":"Peterson_2017","enumerator":"1","doi":"10.1002/9781118786352.wbieg1050","html":"Peterson, P. R. (2017). Discrete Global Grid Systems. In <i>International Encyclopedia of Geography</i> (pp. 1–10). Wiley. <a target=\"_blank\" rel=\"noreferrer\" href=\"https://doi.org/10.1002/9781118786352.wbieg1050\">10.1002/9781118786352.wbieg1050</a>","url":"https://doi.org/10.1002/9781118786352.wbieg1050"},"Gorski_2005":{"label":"Gorski_2005","enumerator":"2","doi":"10.1086/427976","html":"Gorski, K. M., Hivon, E., Banday, A. J., Wandelt, B. D., Hansen, F. K., Reinecke, M., & Bartelmann, M. (2005). HEALPix: A Framework for High‐Resolution Discretization and Fast Analysis of Data Distributed on the Sphere. <i>The Astrophysical Journal</i>, <i>622</i>(2), 759–771. <a target=\"_blank\" rel=\"noreferrer\" href=\"https://doi.org/10.1086/427976\">10.1086/427976</a>","url":"https://doi.org/10.1086/427976"}}}},"footer":{"navigation":{"prev":{"title":"How to Cite This Cookbook","url":"/notebooks/how-to-cite","group":"Preamble"},"next":{"title":"easy.gems for HEALPix Analysis & Visualization","url":"/notebooks/easygems","group":"HEALPix Analysis & Visualization"}}},"domain":"http://localhost:3000"}